[
{"name":"\u0026Run","artist":"Sir Sly","isrc":"USUM71704895"},
{"name":"'Bout It","artist":"Canon","isrc":"TCACL1624927"},
{"name":"1 way ticket","artist":"Lewis Harris","isrc":"XXXXX0000451"},
{"name":"1901","artist":"Phoenix","isrc":"USYAH0700156"},
{"name":"1993","artist":"Approaching Nirvana","isrc":"XXXXX0000031"},
{"name":"1995","artist":"Yours Truly, CC","isrc":"XXXXX0000159"},
{"name":"22","artist":"Taylor Swift","isrc":"USCJY1231214"},
{"name":"2414","artist":"little image","isrc":"XXXXX0000180"},
{"name":"4 You","artist":"DonLear","isrc":"XXXXX0000438"},
{"name":"50 Ways to Say Goodbye","artist":"Train","isrc":"USSM11201533"},
{"name":"865","artist":"Cece Coakley","isrc":"QM7282317317"},
{"name":"A Beautiful Day","artist":"GXNXSIS","isrc":"XXXXX0000497"},
{"name":"A Bouquet Of Daisies","artist":"Staysea","isrc":"XXXXX0000370"},
{"name":"A Fleeting Dabble","artist":"Jaztorius","isrc":"XXXXX0000434"},
{"name":"A Little Bit of Faith","artist":"Kings Kaleidoscope","isrc":"QZES51951008"},
{"name":"A Little Fresh Air","artist":"Paoz","isrc":"XXXXX0000142"},
{"name":"A Moment Apart","artist":"Filae","isrc":"XXXXX0000138"},
{"name":"A Sea of Stars","artist":"Swoozy","isrc":"FXQ892200548"},
{"name":"a thousand years","artist":"Christina Perri","isrc":"USAT21103468"},
{"name":"Above The Clouds","artist":"WanderLight","isrc":"XXXXX0000140"},
{"name":"Acapella","artist":"Karmin","isrc":"USSM11302997"},
{"name":"Achilles Come Down","artist":"Gang of Youths","isrc":"AUBM01700503"},
{"name":"Adore You","artist":"Miley Cyrus","isrc":"USSM12305496"},
{"name":"Afraid","artist":"The Neighbourhood","isrc":"USSM11300889"},
{"name":"After Dark","artist":"kokoro","isrc":"GBLV62127811"},
{"name":"Aimless Knight","artist":"Kings Kaleidoscope","isrc":"QZDA41995746"},
{"name":"Ain't No Mountain High Enough","artist":"Marvin Gaye","isrc":"USAFM0600367"},
{"name":"Ain't No Rest for the Wicked","artist":"Cage The Elephant","isrc":"USJI10900260"},
{"name":"Ain't Nobody (Loves Me Better)","artist":"Felix Jaehn","isrc":"DEUM71501103"},
{"name":"Air Chrysalis","artist":"Animals As Leaders","isrc":"USYFZ1447403"},
{"name":"Alabaster","artist":"luv pug","isrc":"FXQ892200466"},
{"name":"Alizes","artist":"Low Tide","isrc":"XXXXX0000175"},
{"name":"All About That Bass","artist":"Meghan Trainor","isrc":"USSM12410059"},
{"name":"All About You","artist":"Tenda Senda","isrc":"XXXXX0000346"},
{"name":"All Alone","artist":"fun.","isrc":"USAT21104054"},
{"name":"All My Favorite Songs","artist":"Weezer","isrc":"XXXXX0000293"},
{"name":"All My Friends","artist":"Snakehips","isrc":"XXXXX0000226"},
{"name":"All of Me","artist":"Big Gigantic","isrc":"USA2P1679645"},
{"name":"All Time Low","artist":"Jon Bellion","isrc":"USUM71604908"},
{"name":"Alligator Sky","artist":"Owl City","isrc":"USUM71104783"},
{"name":"Along the River","artist":"Leo Motta","isrc":"XXXXX0000096"},
{"name":"always be","artist":"lost.mindd","isrc":"QZFZ42352600"},
{"name":"always you","artist":"Granger","isrc":"XXXXX0000405"},
{"name":"Am I Wrong","artist":"Nico \u0026 Vinz","isrc":"XXXXX0000449"},
{"name":"Amaryllis","artist":"jacuzzi jefferson","isrc":"NL1LE2303327"},
{"name":"Amazing","artist":"Aerosmith","isrc":"XXXXX0000319"},
{"name":"Ambivalent Peaks","artist":"Bad Books","isrc":"US72W1210942"},
{"name":"Ambulance","artist":"Paul Meany","isrc":"XXXXX0000326"},
{"name":"Amen","artist":"for KING \u0026 COUNTRY","isrc":"USM1C1800160"},
{"name":"American Boy","artist":"Estelle","isrc":"XXXXX0000348"},
{"name":"American Oxygen","artist":"Rihanna","isrc":"XXXXX0000445"},
{"name":"Among","artist":"morningtime","isrc":"FXQ892200218"},
{"name":"Analog","artist":"Silky","isrc":"XXXXX0000198"},
{"name":"Angel","artist":"Aerosmith","isrc":"USUG12301904"},
{"name":"Animus Vox","artist":"The Glitch Mob","isrc":"QMBZ92059002"},
{"name":"Anna Sun","artist":"WALK THE MOON","isrc":"USRC11200002"},
{"name":"Another Drink","artist":"Mike Beating","isrc":"XXXXX0000105"},
{"name":"Another Year","artist":"Animals As Leaders","isrc":"USYFZ1447404"},
{"name":"Anyhow...","artist":"Tyler Lyle","isrc":"XXXXX0000072"},
{"name":"Anything Could Happen","artist":"Ellie Goulding","isrc":"GBUV71301575"},
{"name":"Aquarius Apocalyptic","artist":"Stop Light Observations","isrc":"XXXXX0000082"},
{"name":"arms","artist":"Christina Perri","isrc":"USAT21100375"},
{"name":"Around Us","artist":"Jónsi","isrc":"GBKEE1000100"},
{"name":"arrow","artist":"half•alive","isrc":"USRC11803910"},
{"name":"As Far As the East Is from the (Navel to The) West","artist":"Levi The Poet","isrc":"XXXXX0000260"},
{"name":"asphodel","artist":"Tatami Construct","isrc":"GBLV62124730"},
{"name":"Astral Observatory","artist":"Mikel","isrc":"QZMEP2222879"},
{"name":"Astrid","artist":"Bcalm","isrc":"FXQ892200088"},
{"name":"Awakening","artist":"Christopher Larkin","isrc":"QT65W2544165"},
{"name":"Baby Got Back","artist":"Jonathan Coulton","isrc":"XXXXX0000303"},
{"name":"Back To The Surface","artist":"Snowji","isrc":"XXXXX0000407"},
{"name":"Backmask","artist":"Circa Survive","isrc":"USHR21711132"},
{"name":"Bad","artist":"The Cab","isrc":"USUM71300674"},
{"name":"Bad Blood","artist":"Sleeping At Last","isrc":"USGES1480004"},
{"name":"Bad Wings","artist":"The Glitch Mob","isrc":"QMBZ92059003"},
{"name":"Baggage","artist":"Rare Americans","isrc":"TCAFM2169912"},
{"name":"Baixa","artist":"Dinis","isrc":"FXQ892200378"},
{"name":"Balmoral Hotel","artist":"Rare Americans","isrc":"CAGXI1800003"},
{"name":"Bambi","artist":"Hippo Campus","isrc":"QM5BK1800241"},
{"name":"Bang Bang","artist":"Lawrence Taylor","isrc":"XXXXX0000323"},
{"name":"Bang It Out","artist":"Breathe Carolina","isrc":"US5261319002"},
{"name":"Bangups and Hangups","artist":"Earthquake Lights","isrc":"XXXXX0000478"},
{"name":"Battle","artist":"Nicholas Britell","isrc":"USWD12219312"},
{"name":"Battle Scars","artist":"Lupe Fiasco","isrc":"XXXXX0000186"},
{"name":"be my forever","artist":"Christina Perri","isrc":"XXXXX0000318"},
{"name":"Beacon","artist":"Prigida","isrc":"XXXXX0000232"},
{"name":"Beautiful Disaster","artist":"Kelly Clarkson","isrc":"USRC10300798"},
{"name":"Beautiful Thing","artist":"Grace VanderWaal","isrc":"USSM11609210"},
{"name":"Beauty \u0026 Beast","artist":"Pantone","isrc":"XXXXX0000384"},
{"name":"Before the Rain","artist":"Hiyo","isrc":"XXXXX0000460"},
{"name":"Before We Fade","artist":"Tristam","isrc":"CA6D21600186"},
{"name":"Believe","artist":"Mumford \u0026 Sons","isrc":"GBUM71605348"},
{"name":"Believer","artist":"American Authors","isrc":"USUM71302188"},
{"name":"Beneath the Silver Moon","artist":"Matthew Perryman Jones","isrc":"XXXXX0000306"},
{"name":"Beneath Your Beautiful","artist":"Labrinth","isrc":"XXXXX0000224"},
{"name":"Berserker (Album Version)","artist":"Approaching Nirvana","isrc":"XXXXX0000034"},
{"name":"Best Day Of My Life","artist":"American Authors","isrc":"USUM71302187"},
{"name":"Better By Now","artist":"Abby Holliday","isrc":"QZNWT2180594"},
{"name":"Better Than Nothing","artist":"Ray Bull","isrc":"QZFZ22459004"},
{"name":"Big Bang Two","artist":"Chameleon Circuit","isrc":"TCAAZ1103460"},
{"name":"Big Black Car","artist":"Gregory Alan Isakov","isrc":"XXXXX0000309"},
{"name":"Billie Jean","artist":"EDEN","isrc":"GBSMU2417489"},
{"name":"Birch Trees \u0026 Broken Barns","artist":"Caroline Smith \u0026 The Good Night Sleeps","isrc":"USA6B1011002"},
{"name":"Birth of the Economic Hit Man","artist":"Circa Survive","isrc":"USYFZ1452201"},
{"name":"Birthday Baby (The Girl with No Smile)","artist":"Joe P","isrc":"USAT22403182"},
{"name":"Black Mambo","artist":"Glass Animals","isrc":"GBUM71303835"},
{"name":"Black Sun","artist":"Death Cab for Cutie","isrc":"USAT21500029"},
{"name":"Bleeding Love","artist":"Leona Lewis","isrc":"GBARL2200971"},
{"name":"Blink of an Eye","artist":"Mogli the Iceburg","isrc":"TCACO1672080"},
{"name":"Block After Block","artist":"Matt and Kim","isrc":"US4HB1000023"},
{"name":"Blow Yourself","artist":"Altair Blake","isrc":"XXXXX0000403"},
{"name":"Blu","artist":"Jon Bellion","isrc":"USUM71817097"},
{"name":"BLUE DREAM","artist":"sleen.","isrc":"XXXXX0000361"},
{"name":"Blue Pacific","artist":"Bcalm","isrc":"FXQ892200156"},
{"name":"Bluebird","artist":"Anna Tivel","isrc":"XXXXX0000271"},
{"name":"Bluey Theme Tune (Instrument Parade)","artist":"Bluey","isrc":"GBCAD2000577"},
{"name":"Blurred Lines","artist":"Robin Thicke","isrc":"USUM71304524"},
{"name":"Boardwalk","artist":"Tibeauthetraveler","isrc":"FXQ892200132"},
{"name":"Bohemian Rhapsody","artist":"Queen","isrc":"XXXXX0000281"},
{"name":"Bonfire","artist":"Childish Gambino","isrc":"CAUM81129167"},
{"name":"Book Room","artist":"Melt On","isrc":"FXQ892200432"},
{"name":"Born This Way","artist":"Glee Cast","isrc":"USQX91100823"},
{"name":"Bottles","artist":"little image","isrc":"XXXXX0000179"},
{"name":"Boy Lilikoi","artist":"Jónsi","isrc":"GBKEE1000140"},
{"name":"Brasso","artist":"Brandon Roberts","isrc":"USWD12537025"},
{"name":"Brave","artist":"Sara Bareilles","isrc":"USSM11305387"},
{"name":"Breakaway","artist":"Kelly Clarkson","isrc":"USWD10423641"},
{"name":"Breakeven","artist":"The Script","isrc":"GBARL0800926"},
{"name":"Breakfast","artist":"Carabide","isrc":"XXXXX0000367"},
{"name":"Breath of Air","artist":"Grieves","isrc":"XXXXX0000060"},
{"name":"Breathe","artist":"The Brilliance","isrc":"XXXXX0000244"},
{"name":"Breathing Infinity (The Rush, Pt. 1)","artist":"Kings Kaleidoscope","isrc":"QZ4JJ1994913"},
{"name":"Bright","artist":"Echosmith","isrc":"USWB11303168"},
{"name":"Brittle Bones Nicky","artist":"Rare Americans","isrc":"CAGXI1900033"},
{"name":"Brother","artist":"The Brilliance","isrc":"XXXXX0000246"},
{"name":"Bubbly","artist":"Colbie Caillat","isrc":"USUM70731646"},
{"name":"Budapest","artist":"George Ezra","isrc":"GBARL1501701"},
{"name":"Burial on the Presidio Banks","artist":"This Will Destroy You","isrc":"US76L0710412"},
{"name":"Buried Alive","artist":"Logic","isrc":"USUM71414218"},
{"name":"Burn","artist":"Ellie Goulding","isrc":"GBUM71303482"},
{"name":"Burn The House Down","artist":"AJR","isrc":"QMRSZ1801582"},
{"name":"Butterfly","artist":"Jon Batiste","isrc":"USUG12305180"},
{"name":"By The Way","artist":"Red Hot Chili Peppers","isrc":"XXXXX0000254"},
{"name":"Cabin Side","artist":"pucca","isrc":"XXXXX0000475"},
{"name":"California","artist":"Tyler Lyle","isrc":"XXXXX0000074"},
{"name":"Californication","artist":"Red Hot Chili Peppers","isrc":"XXXXX0000250"},
{"name":"Call It What You Want","artist":"Foster The People","isrc":"USSM21100831"},
{"name":"Call Me Maybe","artist":"Carly Rae Jepsen","isrc":"USUM71913476"},
{"name":"Calling Your Name","artist":"Jon Batiste","isrc":"USUG12305176"},
{"name":"Can I Call You Tonight?","artist":"Dayglow","isrc":"TCADL1825079"},
{"name":"Can I Freak Out in the Honda","artist":"Cayden Wemple","isrc":"XXXXX0000422"},
{"name":"Can We Start Over","artist":"Ngyn","isrc":"FXQ892200510"},
{"name":"Can't Hold Us","artist":"Macklemore","isrc":"XXXXX0000193"},
{"name":"Can't Ride In the Sand","artist":"Blasty B","isrc":"XXXXX0000491"},
{"name":"Can't Stop","artist":"Red Hot Chili Peppers","isrc":"XXXXX0000255"},
{"name":"CAN'T STOP THE FEELING! (from DreamWorks Animation's \"TROLLS\")","artist":"Justin Timberlake","isrc":"XXXXX0000415"},
{"name":"Canela","artist":"Mood Lab","isrc":"XXXXX0000496"},
{"name":"cantina band 3 ~ star wars lofi","artist":"Mik","isrc":"QZPJ32251479"},
{"name":"Canvas","artist":"luv pug","isrc":"FXQ892200467"},
{"name":"Cape of Good Hope","artist":"Dirty Doering","isrc":"DESH41900648"},
{"name":"Capsize","artist":"FRENSHIP","isrc":"USSM11605173"},
{"name":"Car Radio","artist":"Twenty One Pilots","isrc":"USAT21402436"},
{"name":"Car Ride","artist":"Silky","isrc":"XXXXX0000207"},
{"name":"Cardiac Arrest","artist":"Bad Suns","isrc":"USVR91316301"},
{"name":"Cardinal","artist":"morningtime","isrc":"FXQ892200038"},
{"name":"Carino","artist":"Finder","isrc":"XXXXX0000402"},
{"name":"Carmine","artist":"Lo-Five","isrc":"XXXXX0000385"},
{"name":"Carnivore","artist":"Bear Attack!","isrc":"XXXXX0000276"},
{"name":"Carry On","artist":"fun.","isrc":"USAT21207097"},
{"name":"Carry Your Throne","artist":"Jon Bellion","isrc":"USUM71413368"},
{"name":"Cat Daddy","artist":"Rej3ctz","isrc":"XXXXX0000182"},
{"name":"Celebrate","artist":"Ingrid Michaelson","isrc":"USVT31500008"},
{"name":"Celebration","artist":"Juliàn","isrc":"XXXXX0000372"},
{"name":"Centuries","artist":"Fall Out Boy","isrc":"USUM71412644"},
{"name":"Chains","artist":"Nick Jonas","isrc":"USUG12301250"},
{"name":"Chapter Eleven: Cul-De-Sac Colonies","artist":"Levi The Poet","isrc":"XXXXX0000261"},
{"name":"Chapter Six: Traditional Values Worldview","artist":"Levi The Poet","isrc":"XXXXX0000262"},
{"name":"Chapter Three: The Great American Game","artist":"Levi The Poet","isrc":"XXXXX0000264"},
{"name":"Charlie","artist":"Red Hot Chili Peppers","isrc":"USWB11402816"},
{"name":"Chasing Cars","artist":"Snow Patrol","isrc":"XXXXX0000121"},
{"name":"Chasing Heaven","artist":"Bassnectar","isrc":"QMLD61404043"},
{"name":"Chasing Sunsets","artist":"Filae","isrc":"XXXXX0000368"},
{"name":"Chatter","artist":"Connor Price","isrc":"QZTB42223711"},
{"name":"Cheap Thrills","artist":"Sia","isrc":"JPB602165219"},
{"name":"Cherry Cake","artist":"Tundra Beats","isrc":"XXXXX0000241"},
{"name":"Childhood Memories","artist":"Solly","isrc":"XXXXX0000315"},
{"name":"Childish","artist":"Maadrhino","isrc":"XXXXX0000210"},
{"name":"CHILL TOUCH","artist":"sleen.","isrc":"XXXXX0000139"},
{"name":"Choke","artist":"I DONT KNOW HOW BUT THEY FOUND ME","isrc":"US5261823023"},
{"name":"Choke 'em Up","artist":"Earthquake Lights","isrc":"XXXXX0000470"},
{"name":"Cigarettes","artist":"The Color and Sound","isrc":"XXXXX0000012"},
{"name":"Cinderella","artist":"Rainbow Kitten Surprise","isrc":"USAT22400516"},
{"name":"Circles","artist":"machineheart","isrc":"USSM11408751"},
{"name":"Citizens","artist":"Jon Guerra","isrc":"XXXXX0000016"},
{"name":"Clay","artist":"Grace VanderWaal","isrc":"USSM11609207"},
{"name":"Cleanse","artist":"S-ilo","isrc":"XXXXX0000206"},
{"name":"Closer","artist":"The Chainsmokers","isrc":"USQX91601347"},
{"name":"Closing the Doors","artist":"Caroline Smith \u0026 The Good Night Sleeps","isrc":"USA6B1011009"},
{"name":"Cloud Surfing","artist":"Toti Cisneros","isrc":"FXQ892200494"},
{"name":"Clouds","artist":"MagFi","isrc":"XXXXX0000427"},
{"name":"Clowder","artist":"Stereo Fear","isrc":"FXQ892200488"},
{"name":"Coalesce","artist":"Banks","isrc":"FXQ892200530"},
{"name":"Cocooning","artist":"Ahntow","isrc":"XXXXX0000474"},
{"name":"Code Monkey","artist":"Jonathan Coulton","isrc":"XXXXX0000305"},
{"name":"Coffee House","artist":"David Armann","isrc":"XXXXX0000429"},
{"name":"Coffee Shop","artist":"Gabb.","isrc":"QMANG2213714"},
{"name":"Cold","artist":"lechiffrebeats","isrc":"FXQ892200441"},
{"name":"Cold Coffee","artist":"Dinis","isrc":"FXQ892200401"},
{"name":"Collide","artist":"Breathe Carolina","isrc":"US5261319005"},
{"name":"Come Hang Out","artist":"AJR","isrc":"USKFE1620001"},
{"name":"Come Onn","artist":"Ethan Tasch","isrc":"QM24S2303301"},
{"name":"Coming Over","artist":"Dillon Francis","isrc":"XXXXX0000231"},
{"name":"Complicated","artist":"Avril Lavigne","isrc":"USAR10200093"},
{"name":"Confessions of a Dangerous Mind","artist":"Logic","isrc":"USUM71904201"},
{"name":"Confident","artist":"IONA","isrc":"XXXXX0000287"},
{"name":"Contemplation","artist":"Dosi","isrc":"XXXXX0000201"},
{"name":"Control","artist":"Halsey","isrc":"USUM72111583"},
{"name":"Cookies \u0026 Cream","artist":"Ruen Brothers","isrc":"XXXXX0000046"},
{"name":"Cooler Than Me - Single Mix","artist":"Mike Posner","isrc":"XXXXX0000185"},
{"name":"Coolin'","artist":"Snazzy","isrc":"XXXXX0000192"},
{"name":"Corcovado","artist":"Low Tide","isrc":"XXXXX0000170"},
{"name":"Cough Syrup","artist":"Young the Giant","isrc":"NLA321191874"},
{"name":"Counting Stars","artist":"OneRepublic","isrc":"USUM71301306"},
{"name":"coyote","artist":"Stop Light Observations","isrc":"XXXXX0000077"},
{"name":"Crank That (Soulja Boy)","artist":"Soulja Boy","isrc":"XXXXX0000329"},
{"name":"creamy","artist":"keebs","isrc":"XXXXX0000441"},
{"name":"creature","artist":"half•alive","isrc":"USRC11901788"},
{"name":"Cruella De Vil","artist":"Bill Lee","isrc":"XXXXX0000297"},
{"name":"Cruising","artist":"Hussain Ali","isrc":"XXXXX0000374"},
{"name":"Crystal Souls","artist":"Headphone Activist","isrc":"XXXXX0000053"},
{"name":"Daft Pretty Boys","artist":"Bad Suns","isrc":"QMRSZ1600419"},
{"name":"Daisies Garden","artist":"Staysea","isrc":"XXXXX0000376"},
{"name":"Dance of the Moonlight Jellies","artist":"Coffee Date","isrc":"QZHN72287427"},
{"name":"Dandelion","artist":"Yours Truly, CC","isrc":"XXXXX0000388"},
{"name":"Danny, Dakota \u0026 the Wishing Well","artist":"A Silent Film","isrc":"GB7XS1200003"},
{"name":"Dark Horse","artist":"Katy Perry","isrc":"XXXXX0000065"},
{"name":"Dark Times","artist":"The Weeknd","isrc":"USUG12102018"},
{"name":"Darkest Hour","artist":"Low Roar","isrc":"USXLG1900101"},
{"name":"Day One","artist":"Silky","isrc":"XXXXX0000205"},
{"name":"Daylight","artist":"Matt and Kim","isrc":"US4HB0915501"},
{"name":"Dear Orphan","artist":"little image","isrc":"XXXXX0000181"},
{"name":"Death Note","artist":"Polyphia","isrc":"XXXXX0000331"},
{"name":"Death of a Bachelor","artist":"Panic! At The Disco","isrc":"USAT21503696"},
{"name":"Deer In The Headlights","artist":"Owl City","isrc":"USUM71104669"},
{"name":"Demons","artist":"Imagine Dragons","isrc":"USUM72311081"},
{"name":"Devil in My Dm","artist":"Mogli the Iceburg","isrc":"TCACZ1702135"},
{"name":"Devil Town","artist":"Cavetown","isrc":"QM87M1805201"},
{"name":"DEVOTION","artist":"meija","isrc":"XXXXX0000339"},
{"name":"Dinosaur Bones","artist":"Stop Light Observations","isrc":"XXXXX0000084"},
{"name":"Disparate Youth","artist":"Santigold","isrc":"GBAHS1100389"},
{"name":"Disposable Camera","artist":"Anna Tivel","isrc":"XXXXX0000273"},
{"name":"Dissolve","artist":"Liquid Stranger","isrc":"XXXXX0000037"},
{"name":"Ditchdigger","artist":"Tyler Lyle","isrc":"XXXXX0000070"},
{"name":"Do My Own Thing","artist":"American Authors","isrc":"USUM71805738"},
{"name":"Do You Want to Build a Snowman?","artist":"Kristen Bell","isrc":"XXXXX0000286"},
{"name":"Does Your Heart Break","artist":"The Brilliance","isrc":"XXXXX0000248"},
{"name":"Dollhouse World","artist":"aespa","isrc":"USUG12507516"},
{"name":"Don't Know What's Come Over You","artist":"Ruen Brothers","isrc":"XXXXX0000045"},
{"name":"Don't Know Why","artist":"Norah Jones","isrc":"USBN20200529"},
{"name":"Don't Let Me Down","artist":"The Chainsmokers","isrc":"USQX91600011"},
{"name":"Don't Stop (Color on the Walls)","artist":"Foster The People","isrc":"USSM11101701"},
{"name":"Don't Take The Money","artist":"Bleachers","isrc":"GBK3W2302681"},
{"name":"Dos Oruguitas","artist":"Sebastian Yatra","isrc":"USWD12112917"},
{"name":"Douceur","artist":"Midnight Sleep","isrc":"XXXXX0000143"},
{"name":"Down","artist":"Marian Hill","isrc":"USUM71601627"},
{"name":"Downhill","artist":"kust","isrc":"XXXXX0000380"},
{"name":"Drank on Accutane","artist":"slimdan","isrc":"QM6N22577757"},
{"name":"Dream Of Mickey Mantle","artist":"Bleachers","isrc":"USRC11700732"},
{"name":"Dreamer","artist":"Low Roar","isrc":"XXXXX0000028"},
{"name":"dreamy","artist":"Linearwave","isrc":"BXCMR2000002"},
{"name":"Drifting","artist":"Van El","isrc":"XXXXX0000133"},
{"name":"Drive By","artist":"Train","isrc":"XXXXX0000069"},
{"name":"Drive It Like You Stole It","artist":"The Glitch Mob","isrc":"QMBZ92059014"},
{"name":"Drops of Jupiter (Tell Me)","artist":"Train","isrc":"XXXXX0000117"},
{"name":"drowning.","artist":"Eden Project","isrc":"GBSMU2044922"},
{"name":"Drumhead Trial","artist":"Protest The Hero","isrc":"XXXXX0000278"},
{"name":"Dusk","artist":"Pantone","isrc":"XXXXX0000383"},
{"name":"Dust We Are and Shall Return","artist":"The Brilliance","isrc":"XXXXX0000247"},
{"name":"Dusty Days","artist":"Stereo Fear","isrc":"XXXXX0000452"},
{"name":"Earned It (Fifty Shades Of Grey)","artist":"The Weeknd","isrc":"XXXXX0000390"},
{"name":"Earth","artist":"Sleeping At Last","isrc":"USGES1480014"},
{"name":"Earth is Special","artist":"StormRoy","isrc":"XXXXX0000433"},
{"name":"Ease","artist":"Devon Rea","isrc":"FXQ892300032"},
{"name":"East of the Bay","artist":"Lucid Keys","isrc":"FXQ892200420"},
{"name":"Easy Days","artist":"Carabide","isrc":"XXXXX0000157"},
{"name":"Elastic Heart","artist":"Sia","isrc":"USRC11400976"},
{"name":"Electric Love","artist":"BØRNS","isrc":"XXXXX0000008"},
{"name":"Embers - Original Mix","artist":"Feed Me","isrc":"XXXXX0000216"},
{"name":"Emperor's New Clothes","artist":"Panic! At The Disco","isrc":"USAT21703888"},
{"name":"Empire State of Mind","artist":"Glee Cast","isrc":"USQX91001007"},
{"name":"End Credits","artist":"EDEN","isrc":"CAR071500317"},
{"name":"Endless","artist":"Signature D","isrc":"XXXXX0000163"},
{"name":"Ends of the Earth","artist":"Lord Huron","isrc":"US53Q1200031"},
{"name":"Enemy, love.","artist":"John Mark McMillan","isrc":"QM4941700001"},
{"name":"Entourage","artist":"milligon","isrc":"XXXXX0000456"},
{"name":"Equinox","artist":"Dpsht","isrc":"XXXXX0000102"},
{"name":"Eternity","artist":"Yours Truly, CC","isrc":"XXXXX0000144"},
{"name":"ethereal","artist":"inertia.","isrc":"UKZGC2307093"},
{"name":"Eulogy","artist":"Nicholas Britell","isrc":"USWD12219311"},
{"name":"Evening Walk","artist":"Hiyo","isrc":"XXXXX0000401"},
{"name":"Eventide","artist":"reysi","isrc":"XXXXX0000400"},
{"name":"Everybody Else","artist":"Pretty Jane","isrc":"XXXXX0000111"},
{"name":"Everybody Talks","artist":"Neon Trees","isrc":"USUM71119189"},
{"name":"Everyone's a Bullet","artist":"Ethan Tasch","isrc":"USA2P2508221"},
{"name":"Everyone's Missing","artist":"Tunde Olaniran","isrc":"USFYQ1505406"},
{"name":"Everything at Once","artist":"Lenka","isrc":"USSM11004327"},
{"name":"Everyway","artist":"Circa Survive","isrc":"USHR21711131"},
{"name":"EW!","artist":"Jimmy Fallon","isrc":"XXXXX0000067"},
{"name":"Exterminate, Regenerate","artist":"Chameleon Circuit","isrc":"USTC90949130"},
{"name":"Fairy Mountain","artist":"Player One","isrc":"XXXXX0000466"},
{"name":"Falling My Arms Again","artist":"Two Muses After","isrc":"XXXXX0000233"},
{"name":"Falling Skies","artist":"501","isrc":"XXXXX0000033"},
{"name":"Fancy","artist":"Iggy Azalea","isrc":"GBUM71401088"},
{"name":"Far Fields","artist":"Christopher Larkin","isrc":"QT65W2544008"},
{"name":"Farther Along","artist":"Josh Garrels","isrc":"XXXXX0000086"},
{"name":"Fate","artist":"Smith, Lyle \u0026 Moore","isrc":"XXXXX0000114"},
{"name":"Fauna","artist":"Van El","isrc":"XXXXX0000355"},
{"name":"Fear On Your Side","artist":"Paul Meany","isrc":"XXXXX0000327"},
{"name":"FEEL GOOD","artist":"MOOD boy","isrc":"XXXXX0000131"},
{"name":"Feel Good Inc.","artist":"Gorillaz","isrc":"GBAYE1001174"},
{"name":"Feel It Still","artist":"Portugal. The Man","isrc":"XXXXX0000068"},
{"name":"Feel So Cold","artist":"Carpetman","isrc":"XXXXX0000490"},
{"name":"Feeling Better With You","artist":"Two Muses After","isrc":"XXXXX0000221"},
{"name":"Feeling Good","artist":"Frances The Mute","isrc":"XXXXX0000366"},
{"name":"Feeling Myself","artist":"Swoozy","isrc":"FXQ892200516"},
{"name":"feels like home","artist":"Chae","isrc":"XXXXX0000419"},
{"name":"Feels Like Summer","artist":"Weezer","isrc":"USAT21700603"},
{"name":"Feliz Navidad","artist":"José Feliciano","isrc":"GBCRL1700065"},
{"name":"Fences","artist":"morningtime","isrc":"FXQ892200035"},
{"name":"Fever Dream","artist":"amlo","isrc":"XXXXX0000389"},
{"name":"Fiji","artist":"Hewie Lou","isrc":"FXQ892300080"},
{"name":"Find You","artist":"Chilltone","isrc":"XXXXX0000392"},
{"name":"Fine By Me","artist":"Andy Grammer","isrc":"USZXT1108633"},
{"name":"Firestone","artist":"Kygo","isrc":"USUS11203189"},
{"name":"Firework","artist":"Katy Perry","isrc":"USCA21002701"},
{"name":"Fireworks - New Beginnings","artist":"Yours Truly, CC","isrc":"XXXXX0000382"},
{"name":"First Call","artist":"Jake Jurant","isrc":"XXXXX0000485"},
{"name":"First Day Of My Life","artist":"Bright Eyes","isrc":"XXXXX0000122"},
{"name":"First Rays","artist":"GlobulDub","isrc":"XXXXX0000211"},
{"name":"First Steps","artist":"Two Scents","isrc":"XXXXX0000115"},
{"name":"Fitzpleasure","artist":"alt-J","isrc":"GBZUZ1200045"},
{"name":"Five Hands","artist":"Brandon Roberts","isrc":"USWD12537016"},
{"name":"Fix You","artist":"Coldplay","isrc":"GBAYE0501398"},
{"name":"Fixer Upper","artist":"Maia Wilson","isrc":"XXXXX0000129"},
{"name":"Flashlight","artist":"Jessie J","isrc":"XXXXX0000345"},
{"name":"Flight Mode","artist":"Mr Sanka","isrc":"GBUM71604466"},
{"name":"Fljótavík","artist":"Sigur Rós","isrc":"GBKEE1100206"},
{"name":"Float","artist":"9T7","isrc":"XXXXX0000151"},
{"name":"Fly a Kite","artist":"little image","isrc":"XXXXX0000177"},
{"name":"Fly High","artist":"Bcalm","isrc":"FXQ892200154"},
{"name":"Folding My Clothes","artist":"Pretty Jane","isrc":"XXXXX0000106"},
{"name":"Fool","artist":"Komachi","isrc":"FXQ892200402"},
{"name":"For Elise","artist":"Saint Motel","isrc":"USAT21602340"},
{"name":"For the First Time in Forever","artist":"Kristen Bell","isrc":"XXXXX0000289"},
{"name":"For the First Time in Forever (Reprise)","artist":"Kristen Bell","isrc":"XXXXX0000502"},
{"name":"Forest Whitaker","artist":"Bad Books","isrc":"US72W1210934"},
{"name":"Forming Up/Unto Stone We Are","artist":"Nicholas Britell","isrc":"USWD12219310"},
{"name":"FourFiveSeconds","artist":"Rihanna","isrc":"USJMT1500001"},
{"name":"Freeway","artist":"Night Cap","isrc":"XXXXX0000448"},
{"name":"Friday Morning","artist":"Van El","isrc":"XXXXX0000360"},
{"name":"fringe politics","artist":"Ethan Regan","isrc":"XXXXX0000024"},
{"name":"Frozen Heart","artist":"Cast - Frozen","isrc":"XXXXX0000302"},
{"name":"Future / Past","artist":"John Mark McMillan","isrc":"QMF921450090"},
{"name":"G.O.A.T.","artist":"Polyphia","isrc":"US3X51840910"},
{"name":"Gaia","artist":"Swoozy","isrc":"FXQ892200513"},
{"name":"Gangnam Style (강남스타일)","artist":"PSY","isrc":"USUM71210283"},
{"name":"get by","artist":"Ethan Regan","isrc":"XXXXX0000027"},
{"name":"Get Up","artist":"Mother Mother","isrc":"CAAUN1800015"},
{"name":"Ghost Town","artist":"Adam Lambert","isrc":"USWB11504556"},
{"name":"Give Me Something","artist":"Jarryd James","isrc":"AUUM71500628"},
{"name":"Give Your Heart a Break","artist":"Demi Lovato","isrc":"USHR11132994"},
{"name":"Glistening Shells","artist":"Lofiium","isrc":"XXXXX0000476"},
{"name":"Glow","artist":"Blasty B","isrc":"FXQ892300027"},
{"name":"Go do","artist":"Jónsi","isrc":"USLS51229206"},
{"name":"God Particle","artist":"Hans Zimmer","isrc":"US4DG0900013"},
{"name":"Gold","artist":"Owl City","isrc":"USUM71204754"},
{"name":"Gold Rush","artist":"Death Cab for Cutie","isrc":"XXXXX0000011"},
{"name":"Gold Web","artist":"Anna Tivel","isrc":"XXXXX0000270"},
{"name":"Golden","artist":"Lucid Keys","isrc":"FXQ892200266"},
{"name":"Golden Days","artist":"Panic! At The Disco","isrc":"USAT21703878"},
{"name":"Gone, Gone, Gone","artist":"Phillip Phillips","isrc":"QMTM61200406"},
{"name":"Goner","artist":"Kids That Fly","isrc":"XXXXX0000104"},
{"name":"Good Feeling","artist":"Flo Rida","isrc":"XXXXX0000259"},
{"name":"Good For You","artist":"Selena Gomez","isrc":"USUM71508741"},
{"name":"Good Good Night","artist":"Roscoe Dash","isrc":"XXXXX0000055"},
{"name":"Good Life","artist":"OneRepublic","isrc":"USUM70999110"},
{"name":"Goodmorning","artist":"Bleachers","isrc":"USRC11700733"},
{"name":"Goodnight, Friend","artist":"Allem Iversom","isrc":"UKZGC2304074"},
{"name":"Gooey","artist":"Glass Animals","isrc":"AUAB01400561"},
{"name":"Gossip Girl","artist":"Grace VanderWaal","isrc":"USSM11609209"},
{"name":"Gratitude","artist":"Yours Truly, CC","isrc":"XXXXX0000162"},
{"name":"Great","artist":"Van El","isrc":"XXXXX0000160"},
{"name":"Grenade","artist":"Bruno Mars","isrc":"USATV1001142"},
{"name":"Greymoor","artist":"Christopher Larkin","isrc":"QT65W2544051"},
{"name":"Groov n Around","artist":"lechiffrebeats","isrc":"FXQ892200451"},
{"name":"Grow Till Tall","artist":"Jónsi","isrc":"GBKEE1000145"},
{"name":"Guap","artist":"Big Sean","isrc":"USUM71214099"},
{"name":"Guillotine","artist":"Jon Bellion","isrc":"USUM71602918"},
{"name":"Hall of Fame","artist":"The Script","isrc":"XXXXX0000310"},
{"name":"Hallelujah","artist":"Panic! At The Disco","isrc":"USAT21703881"},
{"name":"Hangover","artist":"Silky","isrc":"XXXXX0000203"},
{"name":"Happiness: We're All in It Together","artist":"This Will Destroy You","isrc":"XXXXX0000252"},
{"name":"Happy","artist":"lechiffrebeats","isrc":"FXQ892200443"},
{"name":"Happy Pills","artist":"Weathers","isrc":"USRC11600888"},
{"name":"Harbour Lights","artist":"A Silent Film","isrc":"GB7XS1200007"},
{"name":"Hardcore","artist":"Cayden Wemple","isrc":"XXXXX0000432"},
{"name":"Harlem Shake","artist":"Harlem Shake","isrc":"XXXXX0000393"},
{"name":"Harmony Hall","artist":"Vampire Weekend","isrc":"USSM11900250"},
{"name":"Hate That You Know Me","artist":"Bleachers","isrc":"USRC11700734"},
{"name":"Haunted by You","artist":"moonboy","isrc":"XXXXX0000413"},
{"name":"HAVE A GOOD DAY","artist":"sleen.","isrc":"XXXXX0000147"},
{"name":"Headlights","artist":"Robin Schulz","isrc":"XXXXX0000229"},
{"name":"Hear The Deep Call","artist":"Snowji","isrc":"XXXXX0000467"},
{"name":"Heart","artist":"Pantone","isrc":"XXXXX0000240"},
{"name":"Heart Attack","artist":"Demi Lovato","isrc":"USHR11334249"},
{"name":"Heart Runs","artist":"John Mark McMillan","isrc":"TCABU1420501"},
{"name":"Heartbeat","artist":"Childish Gambino","isrc":"USYAH1100351"},
{"name":"Heaven (Butterflies)","artist":"Jacob Collier","isrc":"GBUM72505178"},
{"name":"Heavens","artist":"Filae","isrc":"XXXXX0000161"},
{"name":"Helena Beat","artist":"Foster The People","isrc":"XXXXX0000013"},
{"name":"Herb Garden","artist":"BluntOne","isrc":"XXXXX0000059"},
{"name":"Here","artist":"Alessia Cara","isrc":"USUM71506251"},
{"name":"Here for You","artist":"Kygo","isrc":"XXXXX0000222"},
{"name":"Here's to Never Growing Up","artist":"Avril Lavigne","isrc":"USSM11300965"},
{"name":"Hero","artist":"Family of the Year","isrc":"XXXXX0000075"},
{"name":"Hey There Delilah","artist":"Plain White T's","isrc":"XXXXX0000094"},
{"name":"Hey Ya!","artist":"The Northern Empty","isrc":"XXXXX0000076"},
{"name":"Hey, Soul Sister","artist":"Train","isrc":"USSM10904113"},
{"name":"High Horse","artist":"nobigdyl.","isrc":"XXXXX0000058"},
{"name":"Hijos Del Sol","artist":"Hermanos Gutiérrez","isrc":"XXXXX0000042"},
{"name":"Ho Hey","artist":"The Lumineers","isrc":"XXXXX0000007"},
{"name":"Hold The Record","artist":"Paul Meany","isrc":"XXXXX0000325"},
{"name":"Hollow","artist":"Tori Kelly","isrc":"USUM71516655"},
{"name":"HOLLYWOOD","artist":"WHATUPRG","isrc":"XXXXX0000295"},
{"name":"Holy Ghost","artist":"John Mark McMillan","isrc":"TCABU1420489"},
{"name":"Home - White","artist":"The Dear Hunter","isrc":"XXXXX0000412"},
{"name":"Home To Mama","artist":"Justin Bieber","isrc":"USUM71516816"},
{"name":"Hoppípolla","artist":"Sigur Rós","isrc":"GBKEE2500599"},
{"name":"Houdini","artist":"Foster The People","isrc":"USSM21100885"},
{"name":"House Party","artist":"3OH!3","isrc":"USAT21000798"},
{"name":"How It’s Done","artist":"HUNTR/X","isrc":"QZ8BZ2513508"},
{"name":"How to Find the Good Ones","artist":"Dan Romer","isrc":"USWD12111335"},
{"name":"How to Save a Life","artist":"The Fray","isrc":"USSM10602757"},
{"name":"human","artist":"Christina Perri","isrc":"USAT21304202"},
{"name":"Hurt Feelings","artist":"Flight of the Conchords","isrc":"USSUB0980003"},
{"name":"Hypotheticals","artist":"Lake Street Dive","isrc":"USNO12000091"},
{"name":"Hyrule Field","artist":"Mikel","isrc":"QZMEP2222869"},
{"name":"I Can't Live With You","artist":"Queen","isrc":"XXXXX0000447"},
{"name":"I Don't Know Ya","artist":"Ray Bull","isrc":"QMBZ92452639"},
{"name":"I Don’t Wanna Live Forever (Fifty Shades Darker)","artist":"ZAYN","isrc":"USQ4E1602586"},
{"name":"I Feel It","artist":"Cat Clyde","isrc":"CBBXA2200007"},
{"name":"I Knew You Were Trouble.","artist":"Taylor Swift","isrc":"USCJY1231212"},
{"name":"I Know","artist":"Mowli","isrc":"XXXXX0000387"},
{"name":"I Know (A Little)","artist":"Jacob Collier","isrc":"GBUM72505189"},
{"name":"I Like When You Smile","artist":"noddi","isrc":"XXXXX0000356"},
{"name":"I Miss U","artist":"Retronome","isrc":"FXQ892200084"},
{"name":"I Must Cry Out Loud","artist":"Mother Mother","isrc":"CAAUN1800013"},
{"name":"I Need Her","artist":"Staysea","isrc":"XXXXX0000166"},
{"name":"I Need Your Love","artist":"Calvin Harris","isrc":"XXXXX0000463"},
{"name":"I Never Told You","artist":"Colbie Caillat","isrc":"USUM71200849"},
{"name":"I Really Like You","artist":"Carly Rae Jepsen","isrc":"USUM71501431"},
{"name":"I Said","artist":"Matt and Kim","isrc":"XXXXX0000004"},
{"name":"I Say Fever","artist":"Ramona Falls","isrc":"XXXXX0000256"},
{"name":"I See You","artist":"MISSIO","isrc":"USRC11900302"},
{"name":"I Spend Too Much Time in My Room","artist":"The Band CAMINO","isrc":"TCACQ1635222"},
{"name":"I Want You to Want Me","artist":"Gary Jules","isrc":"XXXXX0000168"},
{"name":"I Was Born To Love You","artist":"Queen","isrc":"XXXXX0000291"},
{"name":"I Was Made For Loving You","artist":"Tori Kelly","isrc":"USUM71505913"},
{"name":"I Wish I Could Take It Back","artist":"Dan Romer","isrc":"USWD12111333"},
{"name":"i wish this never ends","artist":"fleece","isrc":"XXXXX0000118"},
{"name":"I Won't Give Up","artist":"Jason Mraz","isrc":"USEE11200176"},
{"name":"I'll Keep On","artist":"NF","isrc":"USUM71501611"},
{"name":"I'm Not The Only One","artist":"Sam Smith","isrc":"GBUM72207709"},
{"name":"I'm Yours","artist":"Jason Mraz","isrc":"USEE10901222"},
{"name":"I've Done No Wrong","artist":"Earthquake Lights","isrc":"XXXXX0000493"},
{"name":"Icarus","artist":"The Hours","isrc":"TCABK1287741"},
{"name":"If I Ain't Got You","artist":"Alicia Keys","isrc":"USJAY0900296"},
{"name":"If I Die Young","artist":"The Band Perry","isrc":"USUM71120070"},
{"name":"If I Were a Ship","artist":"Hey Ocean!","isrc":"XXXXX0000003"},
{"name":"Ignorantro","artist":"JGivens","isrc":"XXXXX0000061"},
{"name":"II. No Exit","artist":"Childish Gambino","isrc":"USYAH1300227"},
{"name":"II. Worldstar","artist":"Childish Gambino","isrc":"USYAH1300218"},
{"name":"Imagination","artist":"Swink","isrc":"XXXXX0000097"},
{"name":"Immortal","artist":"Abby Holliday","isrc":"QM24S2400719"},
{"name":"imperial march 2 ~ star wars lofi","artist":"Mik","isrc":"QZPJ32252627"},
{"name":"imperial march ~ star wars lofi","artist":"Closed on Sunday","isrc":"XXXXX0000088"},
{"name":"Important","artist":"Michigander","isrc":"QMDA62409742"},
{"name":"In A Room Full Of You","artist":"Finder","isrc":"XXXXX0000294"},
{"name":"In For The Kill - Skrillex Remix","artist":"La Roux","isrc":"XXXXX0000312"},
{"name":"In The Air Tonight","artist":"Phil Collins","isrc":"XXXXX0000334"},
{"name":"in the cafeteria","artist":"vensterbank","isrc":"XXXXX0000116"},
{"name":"In Your Eyes","artist":"After Milo","isrc":"XXXXX0000153"},
{"name":"Inner Assassins","artist":"Animals As Leaders","isrc":"USYFZ1678104"},
{"name":"Into the Unknown","artist":"Idina Menzel","isrc":"USWD11994667"},
{"name":"Isaac's Joint","artist":"IONA","isrc":"XXXXX0000292"},
{"name":"Islands","artist":"Hey Ocean!","isrc":"XXXXX0000001"},
{"name":"It Never Stops","artist":"Bad Books","isrc":"US72W1210935"},
{"name":"It Takes Two","artist":"Tenda Senda","isrc":"XXXXX0000439"},
{"name":"It Will Be Okay","artist":"Signature D","isrc":"FXQ892200384"},
{"name":"It Will Rain","artist":"Bruno Mars","isrc":"USAT21102075"},
{"name":"It's a Good Day","artist":"Filae","isrc":"XXXXX0000155"},
{"name":"It's Almost Friday","artist":"Paoz","isrc":"XXXXX0000375"},
{"name":"It's Alright","artist":"Mother Mother","isrc":"CAAUN1800019"},
{"name":"It's Called: Freefall","artist":"Rainbow Kitten Surprise","isrc":"USAT21800165"},
{"name":"It's Like I Know When Imma See U","artist":"Ethansroom","isrc":"XXXXX0000436"},
{"name":"It's the Most Wonderful Time of the Year","artist":"Andy Williams","isrc":"XXXXX0000472"},
{"name":"It's Time","artist":"Imagine Dragons","isrc":"USUM72311066"},
{"name":"IV. Sweatpants","artist":"Childish Gambino","isrc":"US23A1521145"},
{"name":"jar of hearts","artist":"Christina Perri","isrc":"USAT21001508"},
{"name":"Jelly","artist":"Prigida","isrc":"XXXXX0000239"},
{"name":"Jerusalem, New York, Berlin","artist":"Vampire Weekend","isrc":"USSM11900155"},
{"name":"Jump On It","artist":"Sir Mix-A-Lot","isrc":"USLIC0701184"},
{"name":"Jungle Breakdown","artist":"Brandon Roberts","isrc":"USWD12537011"},
{"name":"Just A Crush","artist":"Grace VanderWaal","isrc":"USSM11708047"},
{"name":"Just A Kiss","artist":"Lady A","isrc":"XXXXX0000488"},
{"name":"Just Give Me a Reason","artist":"P!nk","isrc":"USRC11200786"},
{"name":"Keanu Reeves","artist":"Logic","isrc":"USUM71900414"},
{"name":"Keep","artist":"Mother Mother","isrc":"CAAUN1800024"},
{"name":"Keep Forgiving","artist":"Levi The Poet","isrc":"XXXXX0000258"},
{"name":"Keepy Uppy","artist":"Bluey","isrc":"GBCAD2000578"},
{"name":"Kick in the Door","artist":"Xenia Pax","isrc":"XXXXX0000267"},
{"name":"Kids","artist":"Kyle Dixon \u0026 Michael Stein","isrc":"USLS51683402"},
{"name":"kiki's morning latte","artist":"demon gummies","isrc":"XXXXX0000095"},
{"name":"Kin - Dokkodo Sounds Remix","artist":"Mazoulew","isrc":"XXXXX0000298"},
{"name":"Kindness of a Liar","artist":"Anna Tivel","isrc":"XXXXX0000274"},
{"name":"Kingdom of God","artist":"Jon Guerra","isrc":"XXXXX0000020"},
{"name":"Kings of Summer","artist":"ayokay","isrc":"XXXXX0000480"},
{"name":"Kiss Me Thru The Phone","artist":"Soulja Boy","isrc":"XXXXX0000328"},
{"name":"Kiss the Girl","artist":"Chameleon Circuit","isrc":"TCAAZ1103457"},
{"name":"KYBM","artist":"Tunde Olaniran","isrc":"USFYQ1505403"},
{"name":"Lady","artist":"After Milo","isrc":"XXXXX0000130"},
{"name":"Lala Land","artist":"PiPou","isrc":"XXXXX0000396"},
{"name":"Lapidary","artist":"Banks","isrc":"FXQ892200531"},
{"name":"Lapis-Lazuli","artist":"fox","isrc":"XXXXX0000477"},
{"name":"Last Christmas","artist":"Wham!","isrc":"GB1101100643"},
{"name":"Last Friday Night (T.G.I.F.)","artist":"Katy Perry","isrc":"USUM72121867"},
{"name":"Last Memory","artist":"Jake Jurant","isrc":"XXXXX0000404"},
{"name":"Last Park","artist":"Snowji","isrc":"XXXXX0000149"},
{"name":"Latch","artist":"Sam Smith","isrc":"XXXXX0000457"},
{"name":"Late Afternoon","artist":"Leo Motta","isrc":"XXXXX0000098"},
{"name":"Late Night","artist":"Goson","isrc":"XXXXX0000100"},
{"name":"Late Night Talk","artist":"Low Tide","isrc":"XXXXX0000173"},
{"name":"Late Nights","artist":"Mogli the Iceburg","isrc":"TCACL1654812"},
{"name":"Late Summer","artist":"After Milo","isrc":"XXXXX0000136"},
{"name":"Late Thoughts","artist":"Midnight Sleep","isrc":"XXXXX0000353"},
{"name":"Latent","artist":"Codewav","isrc":"XXXXX0000483"},
{"name":"Lavanda","artist":"Staysea","isrc":"XXXXX0000141"},
{"name":"Lay Me Down","artist":"Sam Smith","isrc":"GBUM71301007"},
{"name":"Lazarus","artist":"Circa Survive","isrc":"XXXXX0000010"},
{"name":"Legend of Lorule","artist":"Mikel","isrc":"QZMEP2222877"},
{"name":"Let Her Go","artist":"Passenger","isrc":"GBMQN1600104"},
{"name":"Let It Go","artist":"Idina Menzel","isrc":"XXXXX0000314"},
{"name":"Let Me Go","artist":"Komachi","isrc":"FXQ892200272"},
{"name":"Let The Quest Begin","artist":"Snowji","isrc":"XXXXX0000421"},
{"name":"Let's Get Married","artist":"Bleachers","isrc":"GBK3W2503377"},
{"name":"Life Of The Party","artist":"Shawn Mendes","isrc":"USUM71616204"},
{"name":"Life's a Beach","artist":"Ray Ben Rue","isrc":"XXXXX0000300"},
{"name":"Light The Sky","artist":"Grace VanderWaal","isrc":"USSM11609208"},
{"name":"Like I Can","artist":"Sam Smith","isrc":"GBUM71308834"},
{"name":"Like I'm Gonna Lose You","artist":"Meghan Trainor","isrc":"XXXXX0000316"},
{"name":"Limitless","artist":"Lotus Beats","isrc":"US3DF2202057"},
{"name":"Link's Awakening","artist":"Mikel","isrc":"QZMEP2222871"},
{"name":"Little Acts Of Violence","artist":"Ray Bull","isrc":"QMDA72481313"},
{"name":"Little Talks","artist":"Of Monsters and Men","isrc":"USUG11300945"},
{"name":"Little Things","artist":"One Direction","isrc":"GBHMU1200529"},
{"name":"Live Without A System","artist":"Carpetman","isrc":"XXXXX0000501"},
{"name":"Locked out of Heaven","artist":"Bruno Mars","isrc":"USAT21204492"},
{"name":"LOL","artist":"Rainbow Kitten Surprise","isrc":"USAT22400504"},
{"name":"Loneliness","artist":"Epic Mountain","isrc":"QZ4JJ1829527"},
{"name":"Long Drives","artist":"BoyWithUke","isrc":"USUG12200347"},
{"name":"Long Way Home","artist":"AK420","isrc":"XXXXX0000209"},
{"name":"Lose Yourself - Soundtrack Version","artist":"Eminem","isrc":"XXXXX0000190"},
{"name":"Loser Like Me","artist":"Glee Cast","isrc":"USQX91100835"},
{"name":"Lost \u0026 Found","artist":"Tyler Lyle","isrc":"XXXXX0000073"},
{"name":"Lost Again","artist":"Filter Feeder","isrc":"XXXXX0000126"},
{"name":"Lost Creek","artist":"Bad Books","isrc":"US72W1210941"},
{"name":"Lost In Space","artist":"Juliàn","isrc":"NLC731600134"},
{"name":"Lost In Translation","artist":"Logic","isrc":"USUM71909026"},
{"name":"Lost Woods","artist":"Player One","isrc":"XXXXX0000344"},
{"name":"Louisiana","artist":"Low Tide","isrc":"XXXXX0000176"},
{"name":"Love + Death","artist":"Kewlie","isrc":"US3DF2291961"},
{"name":"Love Goes On","artist":"Jon Guerra","isrc":"XXXXX0000019"},
{"name":"Love Is All I Bring","artist":"Rare Americans","isrc":"XXXXX0000023"},
{"name":"Love Is an Open Door","artist":"Kristen Bell","isrc":"XXXXX0000127"},
{"name":"Love Lost","artist":"Kichiro","isrc":"XXXXX0000481"},
{"name":"Love Me Again","artist":"John Newman","isrc":"XXXXX0000465"},
{"name":"Love Me Like You Do","artist":"Ellie Goulding","isrc":"XXXXX0000263"},
{"name":"Love Me More","artist":"Tundra Beats","isrc":"XXXXX0000347"},
{"name":"Love Song","artist":"Sara Bareilles","isrc":"XXXXX0000435"},
{"name":"love within","artist":"Linearwave","isrc":"XXXXX0000093"},
{"name":"Love Won't Sleep","artist":"Lostboycrow","isrc":"XXXXX0000322"},
{"name":"Love Yourself","artist":"Justin Bieber","isrc":"USUM71516761"},
{"name":"Low","artist":"TRACE","isrc":"USUS11600246"},
{"name":"Low Sun","artist":"Hermanos Gutiérrez","isrc":"XXXXX0000038"},
{"name":"Luck","artist":"American Authors","isrc":"USUM71309553"},
{"name":"Lucky","artist":"Glee Cast","isrc":"USQX91001142"},
{"name":"Lush Life","artist":"Zara Larsson","isrc":"SEWEE1500509"},
{"name":"Machine Gun Love","artist":"Matthew Perryman Jones","isrc":"XXXXX0000080"},
{"name":"Mad World","artist":"Michael Andrews","isrc":"XXXXX0000337"},
{"name":"Magic","artist":"Coldplay","isrc":"GBAYE1800786"},
{"name":"Magical Feeling","artist":"Midnight Sleep","isrc":"XXXXX0000165"},
{"name":"main title ~ star wars lofi","artist":"Closed on Sunday","isrc":"XXXXX0000090"},
{"name":"Make It Lower","artist":"Carpetman","isrc":"XXXXX0000320"},
{"name":"Make You Happy","artist":"Tundra Beats","isrc":"XXXXX0000354"},
{"name":"Making Contact","artist":"Snazzy","isrc":"XXXXX0000199"},
{"name":"Mandelbrot Set","artist":"Jonathan Coulton","isrc":"XXXXX0000304"},
{"name":"Mansion","artist":"NF","isrc":"USUM71501604"},
{"name":"Marigold","artist":"IONA","isrc":"XXXXX0000381"},
{"name":"Marry You","artist":"Bruno Mars","isrc":"USAT21001887"},
{"name":"Marvin Gaye","artist":"Charlie Puth","isrc":"XXXXX0000379"},
{"name":"Maui","artist":"After Milo","isrc":"XXXXX0000132"},
{"name":"Meet Luca","artist":"Dan Romer","isrc":"USWD12111307"},
{"name":"Meet Me in the Woods","artist":"Lord Huron","isrc":"US53Q1200097"},
{"name":"Meghan's Song","artist":"Matthew Perryman Jones","isrc":"XXXXX0000308"},
{"name":"Memories","artist":"Retronome","isrc":"FXQ892200082"},
{"name":"Meticulous","artist":"Rainbow Kitten Surprise","isrc":"USAT22400506"},
{"name":"Midnight Reverie","artist":"sftspkn","isrc":"FXQ892200193"},
{"name":"midnight walk","artist":"sameO","isrc":"XXXXX0000486"},
{"name":"Migraine","artist":"Twenty One Pilots","isrc":"USAT21202945"},
{"name":"Milk Man","artist":"Rare Americans","isrc":"USAT22004879"},
{"name":"Million Bucks","artist":"Smallpools","isrc":"GBWWP1702933"},
{"name":"Mina Run","artist":"Brandon Roberts","isrc":"USWD12537023"},
{"name":"Mind Tricks","artist":"Bassnectar","isrc":"QMLD61400217"},
{"name":"Mine","artist":"Taylor Swift","isrc":"USCJY1003674"},
{"name":"Mines (Cloth)","artist":"Coffee Date","isrc":"QZHN72287434"},
{"name":"Mirrors","artist":"Justin Timberlake","isrc":"USSM12208049"},
{"name":"Miss Me","artist":"Andy Grammer","isrc":"USZXT1108632"},
{"name":"Miss You","artist":"James Hersey","isrc":"USYAH1600134"},
{"name":"Mizutamari","artist":"Dpsht","isrc":"XXXXX0000107"},
{"name":"Monsters Talk","artist":"John Mark McMillan","isrc":"TCABU1420496"},
{"name":"Moral Of The Story","artist":"Watsky","isrc":"USJPQ1300003"},
{"name":"Morning","artist":"Music Otaku","isrc":"XXXXX0000386"},
{"name":"Motivated","artist":"NF","isrc":"USUM71501607"},
{"name":"Mount Fay","artist":"Christopher Larkin","isrc":"QT65W2544109"},
{"name":"MOVEMENT 18’ (Heroes)","artist":"Jon Batiste","isrc":"USUG12305204"},
{"name":"Mr Handsome","artist":"HBeat","isrc":"XXXXX0000437"},
{"name":"Mr. Blue Sky","artist":"Electric Light Orchestra","isrc":"USSM17200399"},
{"name":"Muddy","artist":"Melt On","isrc":"XXXXX0000397"},
{"name":"Mushroom Walk","artist":"Juliàn","isrc":"XXXXX0000238"},
{"name":"My Body","artist":"Young the Giant","isrc":"NLA321090396"},
{"name":"My Love","artist":"Justin Timberlake","isrc":"USJI10600895"},
{"name":"My My Love","artist":"Joshua Radin","isrc":"XXXXX0000085"},
{"name":"My Name Is Kino Loy","artist":"Nicholas Britell","isrc":"USWD12219297"},
{"name":"My Pain","artist":"Mowli","isrc":"XXXXX0000446"},
{"name":"My Songs Know What You Did In The Dark (Light Em Up)","artist":"Fall Out Boy","isrc":"USV291358671"},
{"name":"My Truest Praise","artist":"Jon Guerra","isrc":"XXXXX0000021"},
{"name":"Mystic Light","artist":"Cat Clyde","isrc":"CBBXA2200005"},
{"name":"Namesake","artist":"Tunde Olaniran","isrc":"USFYQ1505404"},
{"name":"Nasty","artist":"Polyphia","isrc":"XXXXX0000330"},
{"name":"Need You Now - iTunes Session","artist":"Lady A","isrc":"XXXXX0000336"},
{"name":"Never Be Like You","artist":"Flume","isrc":"XXXXX0000218"},
{"name":"New Dawn","artist":"Toti Cisneros","isrc":"FXQ892200495"},
{"name":"New Gold","artist":"Gorillaz","isrc":"XXXXX0000495"},
{"name":"New Machines","artist":"Vinyl Theatre","isrc":"USAT21700222"},
{"name":"Next In Line","artist":"WALK THE MOON","isrc":"USRC11200083"},
{"name":"Next To Me","artist":"Imagine Dragons","isrc":"USUM71704654"},
{"name":"Ni**as In Paris","artist":"JAY-Z","isrc":"USUM71111622"},
{"name":"Night Changes","artist":"One Direction","isrc":"GBHMU1400165"},
{"name":"night out","artist":"kanves","isrc":"XXXXX0000420"},
{"name":"No Matter Where You Are","artist":"Us The Duo","isrc":"USUM71405855"},
{"name":"No One","artist":"Alicia Keys","isrc":"USA2P2319973"},
{"name":"No Other Way","artist":"Snazzy","isrc":"XXXXX0000194"},
{"name":"Nocturn Doubts","artist":"Dosi","isrc":"XXXXX0000191"},
{"name":"Nonstop Pop 2012","artist":"Isosine","isrc":"XXXXX0000265"},
{"name":"Noodle Cup","artist":"fox","isrc":"XXXXX0000416"},
{"name":"Nosebleeds","artist":"slimdan","isrc":"QM4TX2529947"},
{"name":"Not Going Back","artist":"Cat Clyde","isrc":"CBBXA2200003"},
{"name":"Not Your Fault","artist":"AWOLNATION","isrc":"USP6L1000057"},
{"name":"Nothing Left","artist":"Kygo","isrc":"XXXXX0000423"},
{"name":"Nothing Without Love","artist":"Nate Ruess","isrc":"USAT21500169"},
{"name":"Now","artist":"Matt and Kim","isrc":"US4HB1900001"},
{"name":"Now They Know","artist":"Mogli the Iceburg","isrc":"TCACZ1702153"},
{"name":"Numb","artist":"Linkin Park","isrc":"USWB11702186"},
{"name":"O, Virginia","artist":"Matthew Perryman Jones","isrc":"XXXXX0000078"},
{"name":"O.D.","artist":"Polyphia","isrc":"US3X51840902"},
{"name":"Oak Tree (Daydream)","artist":"Arcy Drive","isrc":"QMFME2473010"},
{"name":"Ode to Sleep","artist":"Twenty One Pilots","isrc":"USAT21203005"},
{"name":"Of The Night","artist":"Bastille","isrc":"GBUV71301305"},
{"name":"Oh Darling","artist":"Plug In Stereo","isrc":"XXXXX0000172"},
{"name":"Oh, It Is Love","artist":"Hellogoodbye","isrc":"GBMA21895886"},
{"name":"Ohio Laundry Room","artist":"Abby Holliday","isrc":"QZTB92283338"},
{"name":"ok ok?","artist":"half•alive","isrc":"USRC11901780"},
{"name":"Okinawa Seaside Nap","artist":"Komachi","isrc":"FXQ892300210"},
{"name":"Olympus","artist":"Oh, My.","isrc":"XXXXX0000103"},
{"name":"Omnipotent","artist":"Beautiful Eulogy","isrc":"XXXXX0000056"},
{"name":"On the Way to Work","artist":"Paoz","isrc":"XXXXX0000357"},
{"name":"Once In a While","artist":"Timeflies","isrc":"TCACL1659840"},
{"name":"One Call Away","artist":"Charlie Puth","isrc":"USATV1501158"},
{"name":"One Click Headshot - Original Mix","artist":"Feed Me","isrc":"XXXXX0000215"},
{"name":"One Dance","artist":"Drake","isrc":"USCM51600101"},
{"name":"One Foot","artist":"fun.","isrc":"USAT21102001"},
{"name":"One More Night","artist":"Maroon 5","isrc":"USUM71203514"},
{"name":"One Summer's Day (Spirited Away)","artist":"Sleepy Tom","isrc":"XXXXX0000243"},
{"name":"Only Love","artist":"Mother Mother","isrc":"CAAUN1800022"},
{"name":"Opalite","artist":"Taylor Swift","isrc":"USUMV2503044"},
{"name":"Optimistic Nihilism","artist":"Epic Mountain","isrc":"QZAPG1760360"},
{"name":"Oranges","artist":"Cloudsurfin'","isrc":"XXXXX0000230"},
{"name":"Orion","artist":"Shy Kidx","isrc":"USA6G1352717"},
{"name":"Otherside","artist":"Red Hot Chili Peppers","isrc":"XXXXX0000251"},
{"name":"Out Of My System","artist":"Youngr","isrc":"TCACN1634892"},
{"name":"Over my head","artist":"Judah \u0026 the Lion","isrc":"QMGSG1800003"},
{"name":"Over My Head (Cable Car)","artist":"The Fray","isrc":"USSM10901569"},
{"name":"Over You - Instrumental","artist":"Grieves","isrc":"XXXXX0000202"},
{"name":"overgrown","artist":"jives","isrc":"XXXXX0000150"},
{"name":"Overture","artist":"Sleeping At Last","isrc":"USGES1480001"},
{"name":"Overworlds","artist":"Player One","isrc":"XXXXX0000468"},
{"name":"Owl","artist":"Aisake","isrc":"XXXXX0000363"},
{"name":"Oxygen","artist":"Kings Kaleidoscope","isrc":"QZDA41995748"},
{"name":"P.O.L.I.T.I.C.S.","artist":"MISSIO","isrc":"USRC11900459"},
{"name":"Paixão","artist":"Low Tide","isrc":"XXXXX0000171"},
{"name":"Pandemonium - Original Mix","artist":"Arkasia","isrc":"XXXXX0000223"},
{"name":"Paradise","artist":"Coldplay","isrc":"XXXXX0000178"},
{"name":"Party In The U.S.A.","artist":"Miley Cyrus","isrc":"USHR10924519"},
{"name":"Past/Present Suite","artist":"Nicholas Britell","isrc":"USWD12217415"},
{"name":"Peach","artist":"Glimlip","isrc":"XXXXX0000015"},
{"name":"Pearl","artist":"Signature D","isrc":"XXXXX0000296"},
{"name":"Photograph","artist":"Ed Sheeran","isrc":"GBAHS1400094"},
{"name":"Physical Education","artist":"Animals As Leaders","isrc":"USYFZ1447405"},
{"name":"Pillow Thoughts","artist":"Prigida","isrc":"XXXXX0000227"},
{"name":"Pillowtalk","artist":"Goson","isrc":"XXXXX0000101"},
{"name":"Pitchfork Kids","artist":"AJR","isrc":"USWB11401921"},
{"name":"Playground","artist":"Maadrhino","isrc":"USANG2256590"},
{"name":"Please Don't (Run Away)","artist":"Isosine","isrc":"XXXXX0000268"},
{"name":"Please Don't Go","artist":"Joel Adams","isrc":"AUZN31500442"},
{"name":"Please Don't Say","artist":"Breathe Carolina","isrc":"US5261319006"},
{"name":"Please, Please, Please, Let Me Get What I Want","artist":"The Smiths","isrc":"XXXXX0000453"},
{"name":"Poetic","artist":"Isosine","isrc":"XXXXX0000269"},
{"name":"Poison \u0026 Wine","artist":"The Civil Wars","isrc":"USQX91301426"},
{"name":"Polly","artist":"Prigida","isrc":"XXXXX0000234"},
{"name":"Pompeii","artist":"Bastille","isrc":"GBUM72300585"},
{"name":"Pooh","artist":"pucca","isrc":"XXXXX0000343"},
{"name":"Pools","artist":"lechiffrebeats","isrc":"FXQ892200442"},
{"name":"Poolside Drinks","artist":"Carabide","isrc":"XXXXX0000394"},
{"name":"Poppies","artist":"KNGDAVD","isrc":"XXXXX0000125"},
{"name":"Pork Soda","artist":"Glass Animals","isrc":"GB2DY1600025"},
{"name":"Portra","artist":"Oh, My.","isrc":"FXQ892200368"},
{"name":"Portrait","artist":"Melt On","isrc":"XXXXX0000377"},
{"name":"POSSUM - OPOSSUM","artist":"meija","isrc":"XXXXX0000424"},
{"name":"Pour Toujours","artist":"Pantone","isrc":"XXXXX0000398"},
{"name":"Prayer Man","artist":"Hippo Campus","isrc":"QZPKV2405101"},
{"name":"Present","artist":"Ethan Tasch","isrc":"XXXXX0000169"},
{"name":"Pretender","artist":"Steve Aoki","isrc":"USUS11800131"},
{"name":"Pretty Boy Swag","artist":"Soulja Boy","isrc":"USUM71015217"},
{"name":"Problem Solver","artist":"slimdan","isrc":"QM6MZ2590943"},
{"name":"Prodigal","artist":"Paul Meany","isrc":"XXXXX0000342"},
{"name":"Progress (Indigo)","artist":"The Dear Hunter","isrc":"XXXXX0000284"},
{"name":"Protruding","artist":"Van El","isrc":"XXXXX0000351"},
{"name":"Puddles","artist":"Jordy Chandra","isrc":"XXXXX0000494"},
{"name":"Pumped Up Kicks","artist":"Foster The People","isrc":"XXXXX0000006"},
{"name":"Pure Gold","artist":"half•alive","isrc":"USRC11901784"},
{"name":"Pursuit Of Happiness","artist":"Paoz","isrc":"XXXXX0000426"},
{"name":"Quarterback","artist":"Cayden Wemple","isrc":"XXXXX0000464"},
{"name":"Queen of a Sad Land","artist":"A Silent Film","isrc":"GB7XS1200009"},
{"name":"Quelqu'un M'a Dit","artist":"Carla Bruni","isrc":"FR35O1300106"},
{"name":"Quesadilla","artist":"WALK THE MOON","isrc":"USWLF1000103"},
{"name":"Quiet","artist":"Approaching Nirvana","isrc":"XXXXX0000035"},
{"name":"R.I.P.","artist":"3OH!3","isrc":"USAT21000799"},
{"name":"Rad Drugz","artist":"MISSIO","isrc":"USRC11803854"},
{"name":"Radioactive","artist":"Imagine Dragons","isrc":"USUM72310835"},
{"name":"Radioactive City","artist":"Isosine","isrc":"XXXXX0000266"},
{"name":"Rain Damage","artist":"Grieves","isrc":"XXXXX0000057"},
{"name":"Rain is Beautiful","artist":"StormRoy","isrc":"XXXXX0000461"},
{"name":"Rainy Latte","artist":"Mister Decaf","isrc":"QM3DF2274829"},
{"name":"Rap God","artist":"Eminem","isrc":"USUM71314061"},
{"name":"Rather Be","artist":"Clean Bandit","isrc":"XXXXX0000213"},
{"name":"Rats","artist":"Kyle Dixon \u0026 Michael Stein","isrc":"QZ8BZ1900362"},
{"name":"Reaching Out","artist":"Bassnectar","isrc":"QMLD61400214"},
{"name":"Real","artist":"NF","isrc":"USUM71601379"},
{"name":"REAL ESTATE","artist":"little image","isrc":"XXXXX0000120"},
{"name":"Real Love","artist":"Cat Clyde","isrc":"CBBXA2200006"},
{"name":"Record Player","artist":"Daisy the Great","isrc":"XXXXX0000092"},
{"name":"Red Hands","artist":"Walk off the Earth","isrc":"USSM11205171"},
{"name":"Red Shiny Moon","artist":"MOOD boy","isrc":"XXXXX0000358"},
{"name":"Red Velvet","artist":"Dosi","isrc":"XXXXX0000195"},
{"name":"Redux (Album Version)","artist":"Approaching Nirvana","isrc":"XXXXX0000032"},
{"name":"Reelin","artist":"Ray Bull","isrc":"QM4TW2585215"},
{"name":"Reflect","artist":"Mellow.","isrc":"XXXXX0000409"},
{"name":"Reindeer(s) Are Better Than People","artist":"Jonathan Groff","isrc":"XXXXX0000124"},
{"name":"release","artist":"jives","isrc":"XXXXX0000371"},
{"name":"Relief","artist":"Midnight Sleep","isrc":"FXQ892200111"},
{"name":"Relocation - Original Mix","artist":"Feed Me","isrc":"XXXXX0000219"},
{"name":"Renegades","artist":"X Ambassadors","isrc":"USUM71502643"},
{"name":"Retention","artist":"Misc.Inc","isrc":"XXXXX0000208"},
{"name":"rey's theme ~ star wars lofi","artist":"Closed on Sunday","isrc":"XXXXX0000087"},
{"name":"Ripples","artist":"dxydream","isrc":"XXXXX0000418"},
{"name":"Rippling Brook","artist":"C.enci","isrc":"XXXXX0000411"},
{"name":"Riptide","artist":"Vance Joy","isrc":"USAT21811641"},
{"name":"Rising, Rising - Bassnectar Remix","artist":"Crywolf","isrc":"XXXXX0000443"},
{"name":"River Deep, Mountain High","artist":"Glee Cast","isrc":"USQX91100830"},
{"name":"Roar","artist":"Katy Perry","isrc":"USUV71301934"},
{"name":"Rocking Chair","artist":"Aisake","isrc":"XXXXX0000414"},
{"name":"Rockstar","artist":"BoyWithUke","isrc":"USUG12300948"},
{"name":"Royals","artist":"Lorde","isrc":"NZUM72100629"},
{"name":"Rung","artist":"Prigida","isrc":"XXXXX0000350"},
{"name":"Sacred Land","artist":"BVG","isrc":"GBKQU2321477"},
{"name":"Safe And Sound","artist":"Capital Cities","isrc":"XXXXX0000444"},
{"name":"Sail","artist":"AWOLNATION","isrc":"USPL61000053"},
{"name":"Same Blood","artist":"Kings Kaleidoscope","isrc":"QZDA41995747"},
{"name":"Same Love","artist":"Macklemore \u0026 Ryan Lewis","isrc":"XXXXX0000183"},
{"name":"Samurai Warrior","artist":"Lost Files","isrc":"XXXXX0000113"},
{"name":"San Francisco","artist":"The Mowgli's","isrc":"USUM71213439"},
{"name":"Sand Castle","artist":"Dosi","isrc":"XXXXX0000189"},
{"name":"Sand Castles","artist":"Mowli","isrc":"XXXXX0000167"},
{"name":"Say It","artist":"Flume","isrc":"XXXXX0000217"},
{"name":"Say Something","artist":"A Great Big World","isrc":"US38Y2501756"},
{"name":"Say You Like Me","artist":"We The Kings","isrc":"USZXT1112502"},
{"name":"Saying Things","artist":"Finder","isrc":"XXXXX0000417"},
{"name":"Science Fiction","artist":"Bassnectar","isrc":"QMLD61404052"},
{"name":"Seashells","artist":"Signature D","isrc":"XXXXX0000156"},
{"name":"Seaside","artist":"reysi","isrc":"XXXXX0000137"},
{"name":"Seasons","artist":"Tenda Senda","isrc":"XXXXX0000410"},
{"name":"secrecy","artist":"Ethan Regan","isrc":"XXXXX0000025"},
{"name":"Secrets","artist":"OneRepublic","isrc":"USUM70985644"},
{"name":"Security","artist":"Stop Light Observations","isrc":"XXXXX0000081"},
{"name":"See You Again","artist":"Wiz Khalifa","isrc":"XXXXX0000196"},
{"name":"Sellouts","artist":"Breathe Carolina","isrc":"US5261319003"},
{"name":"Sequoia","artist":"Ruth de las Plantas","isrc":"QM3DF2278603"},
{"name":"Serpents","artist":"Grieves","isrc":"XXXXX0000048"},
{"name":"Sewelo","artist":"Juliàn","isrc":"XXXXX0000430"},
{"name":"Sex \u0026 Candy","artist":"Saturn Night","isrc":"XXXXX0000408"},
{"name":"Shades Of Gray","artist":"Carpetman","isrc":"XXXXX0000489"},
{"name":"Shake It Out","artist":"Florence + The Machine","isrc":"GBUM71108047"},
{"name":"Shake Me Down","artist":"Cage The Elephant","isrc":"USRC11701294"},
{"name":"Shake Your Groove Thing","artist":"Peaches \u0026 Herb","isrc":"XXXXX0000340"},
{"name":"She Will Be Loved","artist":"Maroon 5","isrc":"USJAY0400201"},
{"name":"She'll Be Coming Round the Mountain","artist":"CoComelon","isrc":"UKP3G2004592"},
{"name":"Shia LaBeouf Live","artist":"Rob Cantor","isrc":"TCACA1484522"},
{"name":"Shimmer","artist":"Usman Riaz","isrc":"XXXXX0000503"},
{"name":"Shiver Shiver","artist":"WALK THE MOON","isrc":"USRC11200441"},
{"name":"Shooting Star","artist":"Owl City","isrc":"USSM11300482"},
{"name":"Short Change Hero","artist":"The Heavy","isrc":"GBCFB0901504"},
{"name":"Shots Fired","artist":"Breathe Carolina","isrc":"US5261319004"},
{"name":"Side by Side","artist":"Jacklen Ro","isrc":"XXXXX0000026"},
{"name":"Sienna","artist":"morningtime","isrc":"FXQ892200036"},
{"name":"Silver Flame","artist":"Anna Tivel","isrc":"XXXXX0000272"},
{"name":"Silver Lining","artist":"Mt. Joy","isrc":"USDMG1785501"},
{"name":"Silvertongue","artist":"Young the Giant","isrc":"USAT21601323"},
{"name":"Simple Man","artist":"Shinedown","isrc":"XXXXX0000283"},
{"name":"Sinking Deep","artist":"Hillsong Young \u0026 Free","isrc":"AUHS01305788"},
{"name":"Sinking Friendships","artist":"Jónsi","isrc":"GBKEE1000098"},
{"name":"Sisters","artist":"Saint Motel","isrc":"USAT21905810"},
{"name":"Sk8er Boi","artist":"Avril Lavigne","isrc":"USRC10700291"},
{"name":"Skullclub","artist":"The Glitch Mob","isrc":"QMBZ91303407"},
{"name":"Sky is Majestic","artist":"StormRoy","isrc":"XXXXX0000395"},
{"name":"Skytoucher","artist":"The Glitch Mob","isrc":"QMBZ91303411"},
{"name":"Sleeping Sculpture","artist":"Abby Holliday","isrc":"QM24S2401558"},
{"name":"Slow","artist":"Andy Grammer","isrc":"USZXT1112418"},
{"name":"Slow Down","artist":"Low Roar","isrc":"USXLG1900102"},
{"name":"Slow Draw","artist":"Ruen Brothers","isrc":"XXXXX0000043"},
{"name":"Smile","artist":"lechiffrebeats","isrc":"USANG2255131"},
{"name":"Smoke in the Night","artist":"Grieves","isrc":"XXXXX0000062"},
{"name":"Snowman","artist":"WYS","isrc":"TCAEN1970702"},
{"name":"So Tall","artist":"Melt On","isrc":"FXQ892200460"},
{"name":"Sober","artist":"Kelly Clarkson","isrc":"GBCTA0700098"},
{"name":"Some Nights","artist":"fun.","isrc":"USAT21300230"},
{"name":"Someone Like You","artist":"Adele","isrc":"GBBKS1100251"},
{"name":"Someone New","artist":"Hozier","isrc":"USSM12303630"},
{"name":"Something Heavy","artist":"Jacob Collier","isrc":"GBUM72505253"},
{"name":"something special","artist":"jives","isrc":"XXXXX0000365"},
{"name":"Somewhere Only We Know","artist":"Lily Allen","isrc":"GBAYE1301863"},
{"name":"Song of Storms","artist":"Player One","isrc":"XXXXX0000471"},
{"name":"Sonido Cósmico","artist":"Hermanos Gutiérrez","isrc":"XXXXX0000039"},
{"name":"Sooner Or Later","artist":"Paul Meany","isrc":"XXXXX0000324"},
{"name":"Sorry","artist":"Justin Bieber","isrc":"USUM72202845"},
{"name":"spaceman","artist":"Ethan Regan","isrc":"XXXXX0000022"},
{"name":"Speed Of Love","artist":"Owl City","isrc":"USUM71206285"},
{"name":"Spinnin","artist":"Connor Price","isrc":"QZTAS2238500"},
{"name":"Spit","artist":"Pretty Jane","isrc":"XXXXX0000109"},
{"name":"SPLAT","artist":"Connor Price","isrc":"QZHNB2218020"},
{"name":"SPRING DAYS","artist":"sleen.","isrc":"XXXXX0000154"},
{"name":"Springtime","artist":"bedroom lofi","isrc":"FXQ892300025"},
{"name":"Springy","artist":"Pantone","isrc":"XXXXX0000237"},
{"name":"Stan","artist":"Eminem","isrc":"USUM72509586"},
{"name":"Stand So Close","artist":"Pretty Jane","isrc":"XXXXX0000108"},
{"name":"Stardew Valley Overture","artist":"Coffee Date","isrc":"QZHN72287422"},
{"name":"Stardust","artist":"reysi","isrc":"XXXXX0000455"},
{"name":"Stare Like You'll Stay","artist":"Circa Survive","isrc":"USHR21711130"},
{"name":"Stars","artist":"The xx","isrc":"GBBKS0900242"},
{"name":"Start a Riot","artist":"Duckwrth","isrc":"USUM71820702"},
{"name":"Stay The Night - Featuring Hayley Williams Of Paramore","artist":"Zedd","isrc":"XXXXX0000487"},
{"name":"Stay With Me","artist":"Sam Smith","isrc":"GBCAD1700602"},
{"name":"Steal My Girl","artist":"One Direction","isrc":"GBHMU1400159"},
{"name":"Steezin'","artist":"Hewie Lou","isrc":"FXQ892300108"},
{"name":"Stick to Your Guns","artist":"Watsky","isrc":"XXXXX0000052"},
{"name":"Still Alive (J.C. Mix)","artist":"Aperture Science Psychoacoustic Laboratories","isrc":"XXXXX0000301"},
{"name":"still feel.","artist":"half•alive","isrc":"GBKPL1814938"},
{"name":"Still Waters","artist":"Kainbeats","isrc":"GBKQU2209456"},
{"name":"Stitches","artist":"Shawn Mendes","isrc":"USUM71616208"},
{"name":"Stole the Show","artist":"Kygo","isrc":"XXXXX0000036"},
{"name":"Stolen Dance","artist":"Milky Chance","isrc":"DEL211401622"},
{"name":"Story of My Life","artist":"One Direction","isrc":"GBHMU1400296"},
{"name":"Stranger Things","artist":"Kyle Dixon \u0026 Michael Stein","isrc":"USLS51683401"},
{"name":"Strawberry Chocolate","artist":"MOOD boy","isrc":"XXXXX0000369"},
{"name":"Strawberry Lemonade","artist":"sftspkn","isrc":"XXXXX0000362"},
{"name":"Stressed Out","artist":"Twenty One Pilots","isrc":"USAT21603675"},
{"name":"Stroll in the Park","artist":"Filae","isrc":"XXXXX0000145"},
{"name":"Stronger (What Doesn't Kill You)","artist":"Kelly Clarkson","isrc":"GBCTA1100364"},
{"name":"Stuck Inside","artist":"CaliCronk","isrc":"XXXXX0000275"},
{"name":"Stuck With Me","artist":"Timeflies","isrc":"USUM71510055"},
{"name":"Stupid Deep","artist":"Jon Bellion","isrc":"USUM71817103"},
{"name":"Suit And Jacket","artist":"Judah \u0026 the Lion","isrc":"QMGSG1700002"},
{"name":"Summer","artist":"Calvin Harris","isrc":"XXXXX0000469"},
{"name":"Summer Soul","artist":"Lucid Keys","isrc":"FXQ892200522"},
{"name":"Summer Wind","artist":"Tundra Beats","isrc":"XXXXX0000349"},
{"name":"Sun","artist":"Sleeping At Last","isrc":"USGES1480011"},
{"name":"Sunburst","artist":"kust","isrc":"XXXXX0000235"},
{"name":"Sunday Evening","artist":"Devon Rea","isrc":"FXQ892200179"},
{"name":"Sunflowers","artist":"Signature D","isrc":"XXXXX0000158"},
{"name":"SUNLIGHT","artist":"MOOD boy","isrc":"XXXXX0000135"},
{"name":"Sunny Days","artist":"Lucid Keys","isrc":"XXXXX0000164"},
{"name":"Sunrise","artist":"Kichiro","isrc":"XXXXX0000399"},
{"name":"Sunrise Express","artist":"Oh, My.","isrc":"FXQ892200275"},
{"name":"Sunset","artist":"Phlocalyst","isrc":"US3DF2592844"},
{"name":"Sunset City","artist":"MOOD boy","isrc":"XXXXX0000359"},
{"name":"Sunset Mood","artist":"kanves","isrc":"FXQ892200542"},
{"name":"Sunset With Friends","artist":"Juliàn","isrc":"XXXXX0000225"},
{"name":"Super Lowkey","artist":"JGivens","isrc":"XXXXX0000050"},
{"name":"Superheroes","artist":"The Script","isrc":"GBCAD1400617"},
{"name":"Superposition","artist":"Young the Giant","isrc":"USAT22312386"},
{"name":"Surf City Stroll","artist":"Mamoosh","isrc":"XXXXX0000442"},
{"name":"Surface Pressure","artist":"Jessica Darrow","isrc":"USWD12213778"},
{"name":"SVO","artist":"Rainbow Kitten Surprise","isrc":"USAT22400508"},
{"name":"Sweater Weather","artist":"The Neighbourhood","isrc":"USSM11300080"},
{"name":"Sweet Disposition","artist":"The Temper Trap","isrc":"GBCAD1001270"},
{"name":"Sweet Dreams (Are Made of This)","artist":"Eurythmics","isrc":"GBARL9300075"},
{"name":"Sweet Dreams (Are Made Of This) (Original Mix)","artist":"Eurythmics","isrc":"XXXXX0000313"},
{"name":"Sweet Flower","artist":"Midnight Sleep","isrc":"XXXXX0000146"},
{"name":"Sweet Talk","artist":"Saint Motel","isrc":"USAT21602338"},
{"name":"Swim Between Trees","artist":"flipturn","isrc":"USDMG2580208"},
{"name":"Swimming Pools (Drank)","artist":"DEMAR","isrc":"XXXXX0000009"},
{"name":"Swimming Pools - Instrumental","artist":"Syndicate Sound Labs","isrc":"XXXXX0000128"},
{"name":"Swoon","artist":"Beach Weather","isrc":"TCADD1773910"},
{"name":"Take A Break","artist":"Just Steezy Things","isrc":"UKZGC2305338"},
{"name":"Take a Walk","artist":"Passion Pit","isrc":"USSM21200695"},
{"name":"Take Flight","artist":"thebandfriday","isrc":"QZNWR2487219"},
{"name":"Take It All Back","artist":"Judah \u0026 the Lion","isrc":"QMGSG1500027"},
{"name":"Take It All Back 2.0","artist":"Judah \u0026 the Lion","isrc":"QMGSG1600004"},
{"name":"Take Me to Church","artist":"Hozier","isrc":"GBCAD1600641"},
{"name":"TAKEDOWN (JEONGYEON, JIHYO, CHAEYOUNG)","artist":"TWICE","isrc":"XXXXX0000482"},
{"name":"Taking a Fall","artist":"Colony House","isrc":"XXXXX0000119"},
{"name":"Talk Too Much","artist":"COIN","isrc":"USSM11602662"},
{"name":"Talking to Myself","artist":"Watsky","isrc":"XXXXX0000051"},
{"name":"Tandem","artist":"Protest The Hero","isrc":"USVR91165903"},
{"name":"Teach Us That One Song","artist":"Jon Guerra","isrc":"XXXXX0000017"},
{"name":"Team","artist":"Lorde","isrc":"NZUM71300124"},
{"name":"Tear in My Heart","artist":"Twenty One Pilots","isrc":"XXXXX0000002"},
{"name":"Teardrop","artist":"Massive Attack","isrc":"XXXXX0000333"},
{"name":"Telescope","artist":"Dan Romer","isrc":"USWD12111329"},
{"name":"Tell Me Pretty Lies","artist":"Staysea","isrc":"XXXXX0000134"},
{"name":"Temporary Love","artist":"The Brinks","isrc":"XXXXX0000014"},
{"name":"Tenderly","artist":"The Happy Fits","isrc":"XXXXX0000500"},
{"name":"Tenerife Sea","artist":"Ed Sheeran","isrc":"GBAHS1400096"},
{"name":"Termites","artist":"Protest The Hero","isrc":"USVR91165908"},
{"name":"Tetherball","artist":"Ethan Tasch","isrc":"QM24S2303790"},
{"name":"The A Team","artist":"Ed Sheeran","isrc":"GB6S41000014"},
{"name":"The After Party","artist":"Bad Books","isrc":"US72W1210932"},
{"name":"The Big Bang","artist":"Rock Mafia","isrc":"XXXXX0000066"},
{"name":"The Canopy - Green","artist":"The Dear Hunter","isrc":"XXXXX0000282"},
{"name":"the clones ~ star wars lofi","artist":"Closed on Sunday","isrc":"XXXXX0000089"},
{"name":"The Dark World","artist":"Player One","isrc":"XXXXX0000473"},
{"name":"The Darker The Weather // The Better The Man","artist":"MISSIO","isrc":"USRC11900466"},
{"name":"The Edge","artist":"Panicland","isrc":"CAICR1800003"},
{"name":"The Egg","artist":"Epic Mountain","isrc":"QZFYW2082323"},
{"name":"The Family Madrigal","artist":"Stephanie Beatriz","isrc":"USWD12112911"},
{"name":"The Fear","artist":"Ruen Brothers","isrc":"XXXXX0000047"},
{"name":"The First I love You","artist":"Kyle Dixon \u0026 Michael Stein","isrc":"QZ8BZ1900361"},
{"name":"The Fix","artist":"Earthquake Lights","isrc":"XXXXX0000499"},
{"name":"The Fox (What Does the Fox Say?)","artist":"Ylvis","isrc":"NOAGW1300374"},
{"name":"The Ghosts of Beverly Drive","artist":"Death Cab for Cutie","isrc":"USAT21500033"},
{"name":"The Girl Who Fell From The Sky (Laputa)","artist":"Sleepy Tom","isrc":"XXXXX0000242"},
{"name":"The Gloom","artist":"Cat Clyde","isrc":"CBBXA2200004"},
{"name":"The Good Old Days","artist":"Ale Fillman","isrc":"QMANG2216668"},
{"name":"The Good, the Bad and the Dirty","artist":"Panic! At The Disco","isrc":"USAT21503700"},
{"name":"The Heart Wants What It Wants","artist":"Selena Gomez","isrc":"USHR12244561"},
{"name":"The Hills","artist":"Jake Jurant","isrc":"XXXXX0000352"},
{"name":"The Itch","artist":"Arcy Drive","isrc":"QMFME2476505"},
{"name":"The Kid Wit' Da Flava","artist":"El Jazzy Chavo","isrc":"XXXXX0000063"},
{"name":"The Line (from the series Arcane League of Legends)","artist":"Arcane","isrc":"XXXXX0000288"},
{"name":"The Lotto","artist":"Ingrid Michaelson","isrc":"USKFE1620006"},
{"name":"The Man Who Can't Be Moved","artist":"The Script","isrc":"XXXXX0000450"},
{"name":"the mandalorian ~ star wars lofi","artist":"Closed on Sunday","isrc":"XXXXX0000018"},
{"name":"The Marrow","artist":"Christopher Larkin","isrc":"QT65W2543962"},
{"name":"The Moon Cave","artist":"Gorillaz","isrc":"XXXXX0000228"},
{"name":"The Night We Met","artist":"Lord Huron","isrc":"US53Q1200103"},
{"name":"The One That Got Away","artist":"Katy Perry","isrc":"XXXXX0000440"},
{"name":"The Pocket","artist":"Andy Grammer","isrc":"USZXT1112423"},
{"name":"The Portorosso Cup","artist":"Dan Romer","isrc":"USWD12111334"},
{"name":"The Scientist","artist":"Flux Pavilion","isrc":"GBAHS1300007"},
{"name":"The Show","artist":"Lenka","isrc":"XXXXX0000321"},
{"name":"The Show Goes On","artist":"Lupe Fiasco","isrc":"USAT21002369"},
{"name":"The Show Must Go On","artist":"Queen","isrc":"XXXXX0000280"},
{"name":"The Storm in You","artist":"Ruen Brothers","isrc":"XXXXX0000044"},
{"name":"The Traveller","artist":"Lotus Beats","isrc":"XXXXX0000406"},
{"name":"The Way I Am","artist":"Ingrid Michaelson","isrc":"XXXXX0000307"},
{"name":"The Wind Can Be Still","artist":"Coffee Date","isrc":"QZHN72287433"},
{"name":"Therapy Session","artist":"NF","isrc":"USUM71601375"},
{"name":"There","artist":"morningtime","isrc":"FXQ892200214"},
{"name":"There Are Some Remedies Worse Than the Disease","artist":"This Will Destroy You","isrc":"XXXXX0000253"},
{"name":"There Goes The Fear","artist":"Doves","isrc":"XXXXX0000123"},
{"name":"There You Go","artist":"Komachi","isrc":"FXQ892300169"},
{"name":"There's Nothing Out Here!","artist":"Brandon Roberts","isrc":"USWD12537013"},
{"name":"These Are The Days Of Our Lives","artist":"Queen","isrc":"XXXXX0000484"},
{"name":"These Days","artist":"Connor Price","isrc":"QZMEP2274782"},
{"name":"Think Before I Speak","artist":"Abby Holliday","isrc":"QM24S2403870"},
{"name":"Thinking out Loud","artist":"Ed Sheeran","isrc":"GBAHS2201219"},
{"name":"this is me now","artist":"Martin Luke Brown","isrc":"GBGLW2400894"},
{"name":"This Is What You Came For","artist":"Calvin Harris","isrc":"GB1101501456"},
{"name":"This Isn't You","artist":"Kyle Dixon \u0026 Michael Stein","isrc":"USLS51683404"},
{"name":"This Life","artist":"Vampire Weekend","isrc":"USSM11900141"},
{"name":"This Stage is Your Life","artist":"A Silent Film","isrc":"GB7XS1200002"},
{"name":"Thnks fr th Mmrs","artist":"Fall Out Boy","isrc":"USUM70808155"},
{"name":"Thousand Mile Race","artist":"A Silent Film","isrc":"GB7XS1200011"},
{"name":"Thunder","artist":"Imagine Dragons","isrc":"USUM72310818"},
{"name":"Tightrope","artist":"WALK THE MOON","isrc":"USRC11600131"},
{"name":"Tilting Against Windmills","artist":"Protest The Hero","isrc":"XXXXX0000277"},
{"name":"Timber","artist":"Pitbull","isrc":"USRC11301695"},
{"name":"Time","artist":"Epic Mountain","isrc":"QZ4JJ1775381"},
{"name":"Time After Time","artist":"Cyndi Lauper","isrc":"XXXXX0000335"},
{"name":"Time Bomb","artist":"PYLOT","isrc":"TCAHK2370013"},
{"name":"Toes","artist":"Glass Animals","isrc":"GB2DY1400014"},
{"name":"Together","artist":"GXNXSIS","isrc":"FXQ892200395"},
{"name":"Tokyo Rain","artist":"Komachi","isrc":"FXQ892300209"},
{"name":"Tongue Tied","artist":"GROUPLOVE","isrc":"XXXXX0000005"},
{"name":"Too Close","artist":"Alex Clare","isrc":"GBUM71203569"},
{"name":"Too Good","artist":"Drake","isrc":"USCM51600089"},
{"name":"Too Late","artist":"M83","isrc":"GBSLQ0700009"},
{"name":"Tooth and Claw","artist":"Animals As Leaders","isrc":"USYFZ1447406"},
{"name":"Toxic","artist":"BoyWithUke","isrc":"TCAFS2101442"},
{"name":"Transgressor","artist":"Tunde Olaniran","isrc":"USFYQ1505401"},
{"name":"Trapdoor - Original Mix","artist":"Feed Me","isrc":"XXXXX0000220"},
{"name":"Trichitillomania - Original Mix","artist":"Feed Me","isrc":"XXXXX0000214"},
{"name":"Try","artist":"Colbie Caillat","isrc":"USUM71407113"},
{"name":"Tubthumping","artist":"Chumbawamba","isrc":"XXXXX0000341"},
{"name":"Tuesday","artist":"ILOVEMAKONNEN","isrc":"XXXXX0000054"},
{"name":"Tundra","artist":"milligon","isrc":"XXXXX0000378"},
{"name":"Turn Down for What","artist":"DJ Snake","isrc":"USUM70731278"},
{"name":"Turning Out","artist":"AJR","isrc":"USKFE1620003"},
{"name":"Twentytwofourteen","artist":"The Album Leaf","isrc":"XXXXX0000249"},
{"name":"Two Moons","artist":"BoyWithUke","isrc":"TCAFM2173435"},
{"name":"Two Weeks","artist":"Grizzly Bear","isrc":"GBBPW0900285"},
{"name":"Tying My Shoes","artist":"Caroline Smith \u0026 The Good Night Sleeps","isrc":"USA6B1011005"},
{"name":"Ugly Faces","artist":"Watsky","isrc":"USJPQ1300004"},
{"name":"Um Copo de Felicidade","artist":"IzaBeats","isrc":"XXXXX0000431"},
{"name":"Umbrella","artist":"Hewie Lou","isrc":"FXQ892200290"},
{"name":"Unbearably White","artist":"Vampire Weekend","isrc":"USSM11900144"},
{"name":"Unbelievers","artist":"Vampire Weekend","isrc":"GBBKS1300002"},
{"name":"Under Pressure","artist":"Logic","isrc":"USUM71407322"},
{"name":"under your tongue","artist":"Pretty Jane","isrc":"XXXXX0000110"},
{"name":"Undercover Cops","artist":"slimdan","isrc":"QM4TW2576736"},
{"name":"Underground","artist":"MISSIO","isrc":"USRC11900365"},
{"name":"Understand","artist":"BoyWithUke","isrc":"USUG12201585"},
{"name":"Uneven Odds","artist":"Sleeping At Last","isrc":"USGES1480005"},
{"name":"Until the Dawn Appears","artist":"Matthew Perryman Jones","isrc":"XXXXX0000079"},
{"name":"Until We Meet Again","artist":"Hermanos Gutiérrez","isrc":"XXXXX0000040"},
{"name":"untitled jazz","artist":"coldbrew","isrc":"XXXXX0000299"},
{"name":"Unwind","artist":"Bcalm","isrc":"FXQ892200501"},
{"name":"Us","artist":"Regina Spektor","isrc":"XXXXX0000091"},
{"name":"Vagabond","artist":"Wolfmother","isrc":"AUUM70500118"},
{"name":"Valley","artist":"IONA","isrc":"FXQ892200435"},
{"name":"Vampire on My Fridge","artist":"Low Roar","isrc":"USXLG1400212"},
{"name":"VANDERLIGHT","artist":"Stop Light Observations","isrc":"XXXXX0000083"},
{"name":"VENICE BEACH","artist":"sleen.","isrc":"XXXXX0000152"},
{"name":"Video Games","artist":"Lana Del Rey","isrc":"XXXXX0000257"},
{"name":"Villa Del Refugio","artist":"This Will Destroy You","isrc":"US76L0710407"},
{"name":"Virtual Reality","artist":"xJK.","isrc":"XXXXX0000492"},
{"name":"Vrazil","artist":"Approaching Nirvana","isrc":"XXXXX0000030"},
{"name":"Wait For Me","artist":"Dosi","isrc":"XXXXX0000187"},
{"name":"Waiting (10 Years)","artist":"Low Roar","isrc":"QM5L61700005"},
{"name":"Wake Me Up","artist":"Avicii","isrc":"SEUM71301326"},
{"name":"Wake Up Happy","artist":"Snazzy","isrc":"XXXXX0000200"},
{"name":"Walls","artist":"After Milo","isrc":"XXXXX0000148"},
{"name":"Wandering","artist":"Devon Rea","isrc":"FXQ892200178"},
{"name":"Wanted","artist":"Hunter Hayes","isrc":"USAT21101196"},
{"name":"warm glow","artist":"Hippo Campus","isrc":"QM5BK1700175"},
{"name":"Warm Water","artist":"Jonny Wolf","isrc":"XXXXX0000458"},
{"name":"Way We Live","artist":"Surf Gvng","isrc":"XXXXX0000212"},
{"name":"We Are Never Ever Getting Back Together","artist":"Taylor Swift","isrc":"XXXXX0000064"},
{"name":"We Can't Stop","artist":"Miley Cyrus","isrc":"USRC11300692"},
{"name":"We Don't Know","artist":"Two Muses After","isrc":"XXXXX0000236"},
{"name":"We Don't Talk About Bruno","artist":"Carolina Gaitán","isrc":"USWD12112915"},
{"name":"We Found Love","artist":"Rihanna","isrc":"XXXXX0000428"},
{"name":"We Gathered Leaves","artist":"Linearwave","isrc":"XXXXX0000112"},
{"name":"We No Speak Americano","artist":"Yolanda Be Cool","isrc":"XXXXX0000029"},
{"name":"We No Speak Americano - Original","artist":"Yolanda Be Cool","isrc":"XXXXX0000459"},
{"name":"We Still in this Bitch","artist":"B.o.B","isrc":"XXXXX0000184"},
{"name":"We've Got A Score To Settle - Red","artist":"The Dear Hunter","isrc":"XXXXX0000285"},
{"name":"Weak","artist":"AJR","isrc":"USKFE1620002"},
{"name":"Weightless","artist":"Mellow.","isrc":"XXXXX0000454"},
{"name":"Welcome Home","artist":"Mikel","isrc":"QZMEP2222868"},
{"name":"Werewolf","artist":"Smith, Lyle \u0026 Moore","isrc":"XXXXX0000099"},
{"name":"West Coast","artist":"Dinis","isrc":"FXQ892200377"},
{"name":"Western Bronco","artist":"Hermanos Gutiérrez","isrc":"XXXXX0000041"},
{"name":"Wetlands","artist":"Smith Beats","isrc":"NL4YD2300022"},
{"name":"Wham Bam Shang-A-Lang","artist":"Silver","isrc":"USAR17600150"},
{"name":"What Do You Mean?","artist":"Justin Bieber","isrc":"USUM72202844"},
{"name":"What Is Love - Single Mix","artist":"Haddaway","isrc":"XXXXX0000311"},
{"name":"What Makes You Beautiful","artist":"One Direction","isrc":"GBHMU1200353"},
{"name":"What Time Taught Us - Indigo","artist":"The Dear Hunter","isrc":"XXXXX0000391"},
{"name":"What You Know","artist":"Two Door Cinema Club","isrc":"FRU701200105"},
{"name":"When I Look At You","artist":"Miley Cyrus","isrc":"USHR12447897"},
{"name":"When I Look to the Sky","artist":"Train","isrc":"USSM10304527"},
{"name":"When I Was Your Man","artist":"Bruno Mars","isrc":"USAT21207280"},
{"name":"When the Love Is New","artist":"Shakey Graves","isrc":"XXXXX0000174"},
{"name":"When the Night Falls","artist":"north takoda","isrc":"XXXXX0000462"},
{"name":"Where Did My Apple Fall?","artist":"Jacob Collier","isrc":"GBUM72505182"},
{"name":"Wherever I Am","artist":"Ethan Tasch","isrc":"QM24S2303787"},
{"name":"Wherever You Are","artist":"Jon Batiste","isrc":"USUG12305199"},
{"name":"Whispering Raindrops","artist":"Mr. Donsai","isrc":"XXXXX0000425"},
{"name":"Whistle","artist":"Flo Rida","isrc":"XXXXX0000049"},
{"name":"White Walls","artist":"Macklemore \u0026 Ryan Lewis","isrc":"XXXXX0000188"},
{"name":"Who Let The Dogs Out","artist":"Baha Men","isrc":"XXXXX0000338"},
{"name":"Whoa Whoa Whoa","artist":"Watsky","isrc":"USJPQ1400107"},
{"name":"Why Am I the One","artist":"fun.","isrc":"USAT21300636"},
{"name":"Why Did You Run?","artist":"Judah \u0026 the Lion","isrc":"QMGSG1800007"},
{"name":"Why I Love You","artist":"Mowli","isrc":"XXXXX0000479"},
{"name":"Wild Horseradish Jam","artist":"Coffee Date","isrc":"QZES62201913"},
{"name":"Wildstyle Method","artist":"Bassnectar","isrc":"USQY51081560"},
{"name":"Willow Tree","artist":"reysi","isrc":"FXQ892200253"},
{"name":"Wimbledon White","artist":"slimdan","isrc":"QM6N22577760"},
{"name":"Window","artist":"flipturn","isrc":"USDMG2580207"},
{"name":"Winter Is for Kierkegaard","artist":"Tyler Lyle","isrc":"XXXXX0000071"},
{"name":"Wires","artist":"The Neighbourhood","isrc":"USSM11204648"},
{"name":"Wish You Were Here","artist":"Avril Lavigne","isrc":"USRC11100010"},
{"name":"With U","artist":"SwuM","isrc":"QM2PV1686914"},
{"name":"Without You","artist":"David Guetta","isrc":"XXXXX0000498"},
{"name":"Wobble","artist":"V.I.C.","isrc":"USRE10800620"},
{"name":"Wonderful World","artist":"Solly","isrc":"XXXXX0000317"},
{"name":"Wormholes","artist":"Epic Mountain","isrc":"QZ4JJ1829520"},
{"name":"Worship","artist":"Jon Batiste","isrc":"USUG12305196"},
{"name":"Wrecking Ball","artist":"Miley Cyrus","isrc":"GBCAD1910534"},
{"name":"Yahweh","artist":"The Brilliance","isrc":"XXXXX0000245"},
{"name":"Yas","artist":"Polyphia","isrc":"XXXXX0000332"},
{"name":"Yellow Teeth","artist":"Protest The Hero","isrc":"XXXXX0000279"},
{"name":"You a Star","artist":"Snazzy","isrc":"XXXXX0000197"},
{"name":"You Are a Tourist","artist":"Death Cab for Cutie","isrc":"USAT21500232"},
{"name":"You Can Close Your Eyes","artist":"Jacob Collier","isrc":"GBUM72505177"},
{"name":"You Can't Hold Me Down","artist":"Mogli the Iceburg","isrc":"TCACX1790953"},
{"name":"You Found Me","artist":"The Fray","isrc":"USSM10901572"},
{"name":"You Got Me","artist":"Mowli","isrc":"XXXXX0000373"},
{"name":"You Said","artist":"Connor Price","isrc":"CAJGH1900038"},
{"name":"You're Too Good To Be True","artist":"Finder","isrc":"XXXXX0000290"},
{"name":"You've Haunted Me All My Life","artist":"Death Cab for Cutie","isrc":"USAT21500035"},
{"name":"Young Blood","artist":"The Naked And Famous","isrc":"GBUM71100723"},
{"name":"Your Idol","artist":"Saja Boys","isrc":"QZ8BZ2513512"},
{"name":"Your Shine","artist":"Tundra Beats","isrc":"XXXXX0000364"},
{"name":"Your Song","artist":"Ellie Goulding","isrc":"GBUM71029333"},
{"name":"Yours Truly","artist":"Maadrhino","isrc":"XXXXX0000204"},
{"name":"zumm","artist":"Ngyn","isrc":"FXQ892300006"}
]
